{
  "characteristics_list": [
    {
      "compile": {
        "compilation_success": "yes", 
        "compilation_success_bool": true, 
        "compilation_time": 0.018193960189819336, 
        "compilation_time_with_module": 1.1771280765533447, 
        "joined_compiler_flags": "", 
        "program_git_hash": "43930beba2aa16995b127fe7be131585b5a130aa"
      }, 
      "run": {
        "REAL_ENV_CK_CAFFE_BATCH_SIZE": 12, 
        "REAL_ENV_CK_CAFFE_ITERATIONS": 4166, 
        "REAL_ENV_CK_CAFFE_MODEL": "/home/anton/CK_REPOS/ck-caffe/program/caffe/tmp/tmp-mQzC7h.prototxt", 
        "execution_time": 0.0, 
        "execution_time_with_module": 2.635498046875, 
        "memory_bytes": 99878928, 
        "memory_kbytes": 99878.928, 
        "memory_mbytes": 99.878928, 
        "per_layer_info": [
          {
            "direction": "forward", 
            "index": 0, 
            "label": "00: data", 
            "time_ms": 0.001024, 
            "time_s": 1.024e-06, 
            "timestamp": "1103 15:33:27.857601"
          }, 
          {
            "direction": "backward", 
            "index": 0, 
            "label": "00: data", 
            "time_ms": 0.001216, 
            "time_s": 1.216e-06, 
            "timestamp": "1103 15:33:27.857606"
          }, 
          {
            "direction": "forward", 
            "index": 1, 
            "label": "01: conv1", 
            "time_ms": 1.61568, 
            "time_s": 0.00161568, 
            "timestamp": "1103 15:33:27.857609"
          }, 
          {
            "direction": "backward", 
            "index": 1, 
            "label": "01: conv1", 
            "time_ms": 2.68493, 
            "time_s": 0.0026849300000000003, 
            "timestamp": "1103 15:33:27.857614"
          }, 
          {
            "direction": "forward", 
            "index": 2, 
            "label": "02: relu1", 
            "time_ms": 0.120704, 
            "time_s": 0.000120704, 
            "timestamp": "1103 15:33:27.857616"
          }, 
          {
            "direction": "backward", 
            "index": 2, 
            "label": "02: relu1", 
            "time_ms": 0.001472, 
            "time_s": 1.472e-06, 
            "timestamp": "1103 15:33:27.857620"
          }, 
          {
            "direction": "forward", 
            "index": 3, 
            "label": "03: norm1", 
            "time_ms": 0.369664, 
            "time_s": 0.000369664, 
            "timestamp": "1103 15:33:27.857622"
          }, 
          {
            "direction": "backward", 
            "index": 3, 
            "label": "03: norm1", 
            "time_ms": 1.24006, 
            "time_s": 0.0012400599999999999, 
            "timestamp": "1103 15:33:27.857625"
          }, 
          {
            "direction": "forward", 
            "index": 4, 
            "label": "04: pool1", 
            "time_ms": 0.128, 
            "time_s": 0.000128, 
            "timestamp": "1103 15:33:27.857628"
          }, 
          {
            "direction": "backward", 
            "index": 4, 
            "label": "04: pool1", 
            "time_ms": 0.001344, 
            "time_s": 1.344e-06, 
            "timestamp": "1103 15:33:27.857631"
          }, 
          {
            "direction": "forward", 
            "index": 5, 
            "label": "05: conv2", 
            "time_ms": 2.34906, 
            "time_s": 0.00234906, 
            "timestamp": "1103 15:33:27.857635"
          }, 
          {
            "direction": "backward", 
            "index": 5, 
            "label": "05: conv2", 
            "time_ms": 3.60755, 
            "time_s": 0.0036075499999999997, 
            "timestamp": "1103 15:33:27.857637"
          }, 
          {
            "direction": "forward", 
            "index": 6, 
            "label": "06: relu2", 
            "time_ms": 0.0784, 
            "time_s": 7.84e-05, 
            "timestamp": "1103 15:33:27.857640"
          }, 
          {
            "direction": "backward", 
            "index": 6, 
            "label": "06: relu2", 
            "time_ms": 0.001184, 
            "time_s": 1.184e-06, 
            "timestamp": "1103 15:33:27.857643"
          }, 
          {
            "direction": "forward", 
            "index": 7, 
            "label": "07: norm2", 
            "time_ms": 0.26416, 
            "time_s": 0.00026416, 
            "timestamp": "1103 15:33:27.857646"
          }, 
          {
            "direction": "backward", 
            "index": 7, 
            "label": "07: norm2", 
            "time_ms": 0.961536, 
            "time_s": 0.0009615359999999999, 
            "timestamp": "1103 15:33:27.857650"
          }, 
          {
            "direction": "forward", 
            "index": 8, 
            "label": "08: pool2", 
            "time_ms": 0.086016, 
            "time_s": 8.6016e-05, 
            "timestamp": "1103 15:33:27.857652"
          }, 
          {
            "direction": "backward", 
            "index": 8, 
            "label": "08: pool2", 
            "time_ms": 0.002016, 
            "time_s": 2.016e-06, 
            "timestamp": "1103 15:33:27.857656"
          }, 
          {
            "direction": "forward", 
            "index": 9, 
            "label": "09: conv3", 
            "time_ms": 1.56262, 
            "time_s": 0.00156262, 
            "timestamp": "1103 15:33:27.857658"
          }, 
          {
            "direction": "backward", 
            "index": 9, 
            "label": "09: conv3", 
            "time_ms": 2.08586, 
            "time_s": 0.0020858599999999997, 
            "timestamp": "1103 15:33:27.857661"
          }, 
          {
            "direction": "forward", 
            "index": 10, 
            "label": "10: relu3", 
            "time_ms": 0.02864, 
            "time_s": 2.864e-05, 
            "timestamp": "1103 15:33:27.857664"
          }, 
          {
            "direction": "backward", 
            "index": 10, 
            "label": "10: relu3", 
            "time_ms": 0.001728, 
            "time_s": 1.728e-06, 
            "timestamp": "1103 15:33:27.857667"
          }, 
          {
            "direction": "forward", 
            "index": 11, 
            "label": "11: conv4", 
            "time_ms": 2.11718, 
            "time_s": 0.0021171799999999998, 
            "timestamp": "1103 15:33:27.857671"
          }, 
          {
            "direction": "backward", 
            "index": 11, 
            "label": "11: conv4", 
            "time_ms": 2.51187, 
            "time_s": 0.0025118700000000002, 
            "timestamp": "1103 15:33:27.857673"
          }, 
          {
            "direction": "forward", 
            "index": 12, 
            "label": "12: relu4", 
            "time_ms": 0.028672, 
            "time_s": 2.8672e-05, 
            "timestamp": "1103 15:33:27.857676"
          }, 
          {
            "direction": "backward", 
            "index": 12, 
            "label": "12: relu4", 
            "time_ms": 0.001216, 
            "time_s": 1.216e-06, 
            "timestamp": "1103 15:33:27.857678"
          }, 
          {
            "direction": "forward", 
            "index": 13, 
            "label": "13: conv5", 
            "time_ms": 1.95277, 
            "time_s": 0.00195277, 
            "timestamp": "1103 15:33:27.857682"
          }, 
          {
            "direction": "backward", 
            "index": 13, 
            "label": "13: conv5", 
            "time_ms": 2.02922, 
            "time_s": 0.00202922, 
            "timestamp": "1103 15:33:27.857684"
          }, 
          {
            "direction": "forward", 
            "index": 14, 
            "label": "14: relu5", 
            "time_ms": 0.018432, 
            "time_s": 1.8432000000000002e-05, 
            "timestamp": "1103 15:33:27.857687"
          }, 
          {
            "direction": "backward", 
            "index": 14, 
            "label": "14: relu5", 
            "time_ms": 0.001024, 
            "time_s": 1.024e-06, 
            "timestamp": "1103 15:33:27.857691"
          }, 
          {
            "direction": "forward", 
            "index": 15, 
            "label": "15: pool5", 
            "time_ms": 0.026624, 
            "time_s": 2.6623999999999998e-05, 
            "timestamp": "1103 15:33:27.857693"
          }, 
          {
            "direction": "backward", 
            "index": 15, 
            "label": "15: pool5", 
            "time_ms": 0.00192, 
            "time_s": 1.9200000000000003e-06, 
            "timestamp": "1103 15:33:27.857697"
          }, 
          {
            "direction": "forward", 
            "index": 16, 
            "label": "16: fc6", 
            "time_ms": 1.28614, 
            "time_s": 0.00128614, 
            "timestamp": "1103 15:33:27.857699"
          }, 
          {
            "direction": "backward", 
            "index": 16, 
            "label": "16: fc6", 
            "time_ms": 2.25075, 
            "time_s": 0.00225075, 
            "timestamp": "1103 15:33:27.857702"
          }, 
          {
            "direction": "forward", 
            "index": 17, 
            "label": "17: relu6", 
            "time_ms": 0.006144, 
            "time_s": 6.144e-06, 
            "timestamp": "1103 15:33:27.857705"
          }, 
          {
            "direction": "backward", 
            "index": 17, 
            "label": "17: relu6", 
            "time_ms": 0.001696, 
            "time_s": 1.6960000000000002e-06, 
            "timestamp": "1103 15:33:27.857708"
          }, 
          {
            "direction": "forward", 
            "index": 18, 
            "label": "18: drop6", 
            "time_ms": 0.014336, 
            "time_s": 1.4336e-05, 
            "timestamp": "1103 15:33:27.857712"
          }, 
          {
            "direction": "backward", 
            "index": 18, 
            "label": "18: drop6", 
            "time_ms": 0.001024, 
            "time_s": 1.024e-06, 
            "timestamp": "1103 15:33:27.857714"
          }, 
          {
            "direction": "forward", 
            "index": 19, 
            "label": "19: fc7", 
            "time_ms": 0.576512, 
            "time_s": 0.000576512, 
            "timestamp": "1103 15:33:27.857717"
          }, 
          {
            "direction": "backward", 
            "index": 19, 
            "label": "19: fc7", 
            "time_ms": 1.1407, 
            "time_s": 0.0011407000000000001, 
            "timestamp": "1103 15:33:27.857720"
          }, 
          {
            "direction": "forward", 
            "index": 20, 
            "label": "20: relu7", 
            "time_ms": 0.006816, 
            "time_s": 6.8160000000000005e-06, 
            "timestamp": "1103 15:33:27.857728"
          }, 
          {
            "direction": "backward", 
            "index": 20, 
            "label": "20: relu7", 
            "time_ms": 0.001024, 
            "time_s": 1.024e-06, 
            "timestamp": "1103 15:33:27.857735"
          }, 
          {
            "direction": "forward", 
            "index": 21, 
            "label": "21: drop7", 
            "time_ms": 0.013312, 
            "time_s": 1.3311999999999999e-05, 
            "timestamp": "1103 15:33:27.857739"
          }, 
          {
            "direction": "backward", 
            "index": 21, 
            "label": "21: drop7", 
            "time_ms": 0.00128, 
            "time_s": 1.28e-06, 
            "timestamp": "1103 15:33:27.857743"
          }, 
          {
            "direction": "forward", 
            "index": 22, 
            "label": "22: fc8", 
            "time_ms": 0.14336, 
            "time_s": 0.00014335999999999998, 
            "timestamp": "1103 15:33:27.857745"
          }, 
          {
            "direction": "backward", 
            "index": 22, 
            "label": "22: fc8", 
            "time_ms": 0.484096, 
            "time_s": 0.00048409600000000005, 
            "timestamp": "1103 15:33:27.857748"
          }, 
          {
            "direction": "forward", 
            "index": 23, 
            "label": "23: prob", 
            "time_ms": 0.134144, 
            "time_s": 0.00013414400000000002, 
            "timestamp": "1103 15:33:27.857751"
          }, 
          {
            "direction": "backward", 
            "index": 23, 
            "label": "23: prob", 
            "time_ms": 0.113664, 
            "time_s": 0.000113664, 
            "timestamp": "1103 15:33:27.857754"
          }
        ], 
        "post_processed": "yes", 
        "repeat": 1, 
        "return_code": 0, 
        "run_success": "yes", 
        "run_success_bool": true, 
        "time_bw_ms": 19.2752, 
        "time_bw_s": 0.019275200000000003, 
        "time_fw_ms": 13.0693, 
        "time_fw_s": 0.0130693, 
        "time_fwbw_ms": 32.552, 
        "time_fwbw_s": 0.032552, 
        "time_total_ms": 32.552, 
        "time_total_ms_kernel_0": 32.552, 
        "time_total_s": 0.032552, 
        "time_total_s_kernel_0": 0.032552, 
        "total_execution_time": 0.0
      }
    }, 
    {
      "run": {
        "REAL_ENV_CK_CAFFE_BATCH_SIZE": 12, 
        "REAL_ENV_CK_CAFFE_ITERATIONS": 4166, 
        "REAL_ENV_CK_CAFFE_MODEL": "/home/anton/CK_REPOS/ck-caffe/program/caffe/tmp/tmp-aXRqfM.prototxt", 
        "execution_time": 0.0, 
        "execution_time_with_module": 2.620882034301758, 
        "memory_bytes": 99878928, 
        "memory_kbytes": 99878.928, 
        "memory_mbytes": 99.878928, 
        "per_layer_info": [
          {
            "direction": "forward", 
            "index": 0, 
            "label": "00: data", 
            "time_ms": 0.002048, 
            "time_s": 2.048e-06, 
            "timestamp": "1103 15:33:30.741811"
          }, 
          {
            "direction": "backward", 
            "index": 0, 
            "label": "00: data", 
            "time_ms": 0.001856, 
            "time_s": 1.856e-06, 
            "timestamp": "1103 15:33:30.741816"
          }, 
          {
            "direction": "forward", 
            "index": 1, 
            "label": "01: conv1", 
            "time_ms": 1.60522, 
            "time_s": 0.00160522, 
            "timestamp": "1103 15:33:30.741818"
          }, 
          {
            "direction": "backward", 
            "index": 1, 
            "label": "01: conv1", 
            "time_ms": 2.67264, 
            "time_s": 0.00267264, 
            "timestamp": "1103 15:33:30.741822"
          }, 
          {
            "direction": "forward", 
            "index": 2, 
            "label": "02: relu1", 
            "time_ms": 0.12064, 
            "time_s": 0.00012064, 
            "timestamp": "1103 15:33:30.741824"
          }, 
          {
            "direction": "backward", 
            "index": 2, 
            "label": "02: relu1", 
            "time_ms": 0.001024, 
            "time_s": 1.024e-06, 
            "timestamp": "1103 15:33:30.741827"
          }, 
          {
            "direction": "forward", 
            "index": 3, 
            "label": "03: norm1", 
            "time_ms": 0.371712, 
            "time_s": 0.000371712, 
            "timestamp": "1103 15:33:30.741830"
          }, 
          {
            "direction": "backward", 
            "index": 3, 
            "label": "03: norm1", 
            "time_ms": 1.23904, 
            "time_s": 0.0012390399999999998, 
            "timestamp": "1103 15:33:30.741833"
          }, 
          {
            "direction": "forward", 
            "index": 4, 
            "label": "04: pool1", 
            "time_ms": 0.128, 
            "time_s": 0.000128, 
            "timestamp": "1103 15:33:30.741837"
          }, 
          {
            "direction": "backward", 
            "index": 4, 
            "label": "04: pool1", 
            "time_ms": 0.002048, 
            "time_s": 2.048e-06, 
            "timestamp": "1103 15:33:30.741838"
          }, 
          {
            "direction": "forward", 
            "index": 5, 
            "label": "05: conv2", 
            "time_ms": 2.34787, 
            "time_s": 0.00234787, 
            "timestamp": "1103 15:33:30.741842"
          }, 
          {
            "direction": "backward", 
            "index": 5, 
            "label": "05: conv2", 
            "time_ms": 3.62899, 
            "time_s": 0.00362899, 
            "timestamp": "1103 15:33:30.741844"
          }, 
          {
            "direction": "forward", 
            "index": 6, 
            "label": "06: relu2", 
            "time_ms": 0.0768, 
            "time_s": 7.68e-05, 
            "timestamp": "1103 15:33:30.741847"
          }, 
          {
            "direction": "backward", 
            "index": 6, 
            "label": "06: relu2", 
            "time_ms": 0.001824, 
            "time_s": 1.8240000000000002e-06, 
            "timestamp": "1103 15:33:30.741850"
          }, 
          {
            "direction": "forward", 
            "index": 7, 
            "label": "07: norm2", 
            "time_ms": 0.263168, 
            "time_s": 0.00026316800000000004, 
            "timestamp": "1103 15:33:30.741853"
          }, 
          {
            "direction": "backward", 
            "index": 7, 
            "label": "07: norm2", 
            "time_ms": 0.954368, 
            "time_s": 0.000954368, 
            "timestamp": "1103 15:33:30.741855"
          }, 
          {
            "direction": "forward", 
            "index": 8, 
            "label": "08: pool2", 
            "time_ms": 0.086944, 
            "time_s": 8.6944e-05, 
            "timestamp": "1103 15:33:30.741858"
          }, 
          {
            "direction": "backward", 
            "index": 8, 
            "label": "08: pool2", 
            "time_ms": 0.002048, 
            "time_s": 2.048e-06, 
            "timestamp": "1103 15:33:30.741861"
          }, 
          {
            "direction": "forward", 
            "index": 9, 
            "label": "09: conv3", 
            "time_ms": 1.5592, 
            "time_s": 0.0015592, 
            "timestamp": "1103 15:33:30.741864"
          }, 
          {
            "direction": "backward", 
            "index": 9, 
            "label": "09: conv3", 
            "time_ms": 2.02006, 
            "time_s": 0.00202006, 
            "timestamp": "1103 15:33:30.741868"
          }, 
          {
            "direction": "forward", 
            "index": 10, 
            "label": "10: relu3", 
            "time_ms": 0.028672, 
            "time_s": 2.8672e-05, 
            "timestamp": "1103 15:33:30.741869"
          }, 
          {
            "direction": "backward", 
            "index": 10, 
            "label": "10: relu3", 
            "time_ms": 0.001152, 
            "time_s": 1.1520000000000002e-06, 
            "timestamp": "1103 15:33:30.741873"
          }, 
          {
            "direction": "forward", 
            "index": 11, 
            "label": "11: conv4", 
            "time_ms": 2.12173, 
            "time_s": 0.00212173, 
            "timestamp": "1103 15:33:30.741875"
          }, 
          {
            "direction": "backward", 
            "index": 11, 
            "label": "11: conv4", 
            "time_ms": 2.50538, 
            "time_s": 0.00250538, 
            "timestamp": "1103 15:33:30.741878"
          }, 
          {
            "direction": "forward", 
            "index": 12, 
            "label": "12: relu4", 
            "time_ms": 0.02848, 
            "time_s": 2.848e-05, 
            "timestamp": "1103 15:33:30.741881"
          }, 
          {
            "direction": "backward", 
            "index": 12, 
            "label": "12: relu4", 
            "time_ms": 0.001088, 
            "time_s": 1.088e-06, 
            "timestamp": "1103 15:33:30.741884"
          }, 
          {
            "direction": "forward", 
            "index": 13, 
            "label": "13: conv5", 
            "time_ms": 1.95475, 
            "time_s": 0.00195475, 
            "timestamp": "1103 15:33:30.741886"
          }, 
          {
            "direction": "backward", 
            "index": 13, 
            "label": "13: conv5", 
            "time_ms": 2.02838, 
            "time_s": 0.0020283799999999998, 
            "timestamp": "1103 15:33:30.741889"
          }, 
          {
            "direction": "forward", 
            "index": 14, 
            "label": "14: relu5", 
            "time_ms": 0.018432, 
            "time_s": 1.8432000000000002e-05, 
            "timestamp": "1103 15:33:30.741892"
          }, 
          {
            "direction": "backward", 
            "index": 14, 
            "label": "14: relu5", 
            "time_ms": 0.0016, 
            "time_s": 1.6000000000000001e-06, 
            "timestamp": "1103 15:33:30.741895"
          }, 
          {
            "direction": "forward", 
            "index": 15, 
            "label": "15: pool5", 
            "time_ms": 0.026624, 
            "time_s": 2.6623999999999998e-05, 
            "timestamp": "1103 15:33:30.741897"
          }, 
          {
            "direction": "backward", 
            "index": 15, 
            "label": "15: pool5", 
            "time_ms": 0.001088, 
            "time_s": 1.088e-06, 
            "timestamp": "1103 15:33:30.741900"
          }, 
          {
            "direction": "forward", 
            "index": 16, 
            "label": "16: fc6", 
            "time_ms": 1.28512, 
            "time_s": 0.00128512, 
            "timestamp": "1103 15:33:30.741904"
          }, 
          {
            "direction": "backward", 
            "index": 16, 
            "label": "16: fc6", 
            "time_ms": 2.25366, 
            "time_s": 0.00225366, 
            "timestamp": "1103 15:33:30.741906"
          }, 
          {
            "direction": "forward", 
            "index": 17, 
            "label": "17: relu6", 
            "time_ms": 0.006144, 
            "time_s": 6.144e-06, 
            "timestamp": "1103 15:33:30.741909"
          }, 
          {
            "direction": "backward", 
            "index": 17, 
            "label": "17: relu6", 
            "time_ms": 0.001024, 
            "time_s": 1.024e-06, 
            "timestamp": "1103 15:33:30.741912"
          }, 
          {
            "direction": "forward", 
            "index": 18, 
            "label": "18: drop6", 
            "time_ms": 0.01536, 
            "time_s": 1.5360000000000002e-05, 
            "timestamp": "1103 15:33:30.741914"
          }, 
          {
            "direction": "backward", 
            "index": 18, 
            "label": "18: drop6", 
            "time_ms": 0.001024, 
            "time_s": 1.024e-06, 
            "timestamp": "1103 15:33:30.741917"
          }, 
          {
            "direction": "forward", 
            "index": 19, 
            "label": "19: fc7", 
            "time_ms": 0.57856, 
            "time_s": 0.00057856, 
            "timestamp": "1103 15:33:30.741920"
          }, 
          {
            "direction": "backward", 
            "index": 19, 
            "label": "19: fc7", 
            "time_ms": 1.152, 
            "time_s": 0.001152, 
            "timestamp": "1103 15:33:30.741924"
          }, 
          {
            "direction": "forward", 
            "index": 20, 
            "label": "20: relu7", 
            "time_ms": 0.006144, 
            "time_s": 6.144e-06, 
            "timestamp": "1103 15:33:30.741930"
          }, 
          {
            "direction": "backward", 
            "index": 20, 
            "label": "20: relu7", 
            "time_ms": 0.001408, 
            "time_s": 1.408e-06, 
            "timestamp": "1103 15:33:30.741940"
          }, 
          {
            "direction": "forward", 
            "index": 21, 
            "label": "21: drop7", 
            "time_ms": 0.012896, 
            "time_s": 1.2896e-05, 
            "timestamp": "1103 15:33:30.741942"
          }, 
          {
            "direction": "backward", 
            "index": 21, 
            "label": "21: drop7", 
            "time_ms": 0.001408, 
            "time_s": 1.408e-06, 
            "timestamp": "1103 15:33:30.741945"
          }, 
          {
            "direction": "forward", 
            "index": 22, 
            "label": "22: fc8", 
            "time_ms": 0.14336, 
            "time_s": 0.00014335999999999998, 
            "timestamp": "1103 15:33:30.741947"
          }, 
          {
            "direction": "backward", 
            "index": 22, 
            "label": "22: fc8", 
            "time_ms": 0.484352, 
            "time_s": 0.000484352, 
            "timestamp": "1103 15:33:30.741950"
          }, 
          {
            "direction": "forward", 
            "index": 23, 
            "label": "23: prob", 
            "time_ms": 0.13472, 
            "time_s": 0.00013472, 
            "timestamp": "1103 15:33:30.741953"
          }, 
          {
            "direction": "backward", 
            "index": 23, 
            "label": "23: prob", 
            "time_ms": 0.109568, 
            "time_s": 0.000109568, 
            "timestamp": "1103 15:33:30.741956"
          }
        ], 
        "post_processed": "yes", 
        "repeat": 1, 
        "return_code": 0, 
        "run_success": "yes", 
        "run_success_bool": true, 
        "time_bw_ms": 19.2144, 
        "time_bw_s": 0.019214400000000003, 
        "time_fw_ms": 13.0613, 
        "time_fw_s": 0.0130613, 
        "time_fwbw_ms": 32.4721, 
        "time_fwbw_s": 0.0324721, 
        "time_total_ms": 32.4721, 
        "time_total_ms_kernel_0": 32.4721, 
        "time_total_s": 0.0324721, 
        "time_total_s_kernel_0": 0.0324721, 
        "total_execution_time": 0.0
      }
    }, 
    {
      "run": {
        "REAL_ENV_CK_CAFFE_BATCH_SIZE": 12, 
        "REAL_ENV_CK_CAFFE_ITERATIONS": 4166, 
        "REAL_ENV_CK_CAFFE_MODEL": "/home/anton/CK_REPOS/ck-caffe/program/caffe/tmp/tmp-wYuDij.prototxt", 
        "execution_time": 0.0, 
        "execution_time_with_module": 2.5568530559539795, 
        "memory_bytes": 99878928, 
        "memory_kbytes": 99878.928, 
        "memory_mbytes": 99.878928, 
        "per_layer_info": [
          {
            "direction": "forward", 
            "index": 0, 
            "label": "00: data", 
            "time_ms": 0.002048, 
            "time_s": 2.048e-06, 
            "timestamp": "1103 15:33:33.595698"
          }, 
          {
            "direction": "backward", 
            "index": 0, 
            "label": "00: data", 
            "time_ms": 0.0016, 
            "time_s": 1.6000000000000001e-06, 
            "timestamp": "1103 15:33:33.595703"
          }, 
          {
            "direction": "forward", 
            "index": 1, 
            "label": "01: conv1", 
            "time_ms": 1.58822, 
            "time_s": 0.00158822, 
            "timestamp": "1103 15:33:33.595707"
          }, 
          {
            "direction": "backward", 
            "index": 1, 
            "label": "01: conv1", 
            "time_ms": 2.68166, 
            "time_s": 0.0026816599999999998, 
            "timestamp": "1103 15:33:33.595710"
          }, 
          {
            "direction": "forward", 
            "index": 2, 
            "label": "02: relu1", 
            "time_ms": 0.119808, 
            "time_s": 0.000119808, 
            "timestamp": "1103 15:33:33.595713"
          }, 
          {
            "direction": "backward", 
            "index": 2, 
            "label": "02: relu1", 
            "time_ms": 0.001792, 
            "time_s": 1.792e-06, 
            "timestamp": "1103 15:33:33.595715"
          }, 
          {
            "direction": "forward", 
            "index": 3, 
            "label": "03: norm1", 
            "time_ms": 0.372736, 
            "time_s": 0.00037273600000000003, 
            "timestamp": "1103 15:33:33.595719"
          }, 
          {
            "direction": "backward", 
            "index": 3, 
            "label": "03: norm1", 
            "time_ms": 1.23965, 
            "time_s": 0.00123965, 
            "timestamp": "1103 15:33:33.595721"
          }, 
          {
            "direction": "forward", 
            "index": 4, 
            "label": "04: pool1", 
            "time_ms": 0.128, 
            "time_s": 0.000128, 
            "timestamp": "1103 15:33:33.595724"
          }, 
          {
            "direction": "backward", 
            "index": 4, 
            "label": "04: pool1", 
            "time_ms": 0.001792, 
            "time_s": 1.792e-06, 
            "timestamp": "1103 15:33:33.595727"
          }, 
          {
            "direction": "forward", 
            "index": 5, 
            "label": "05: conv2", 
            "time_ms": 2.34266, 
            "time_s": 0.00234266, 
            "timestamp": "1103 15:33:33.595731"
          }, 
          {
            "direction": "backward", 
            "index": 5, 
            "label": "05: conv2", 
            "time_ms": 3.7199, 
            "time_s": 0.0037199, 
            "timestamp": "1103 15:33:33.595733"
          }, 
          {
            "direction": "forward", 
            "index": 6, 
            "label": "06: relu2", 
            "time_ms": 0.078848, 
            "time_s": 7.8848e-05, 
            "timestamp": "1103 15:33:33.595736"
          }, 
          {
            "direction": "backward", 
            "index": 6, 
            "label": "06: relu2", 
            "time_ms": 0.001184, 
            "time_s": 1.184e-06, 
            "timestamp": "1103 15:33:33.595739"
          }, 
          {
            "direction": "forward", 
            "index": 7, 
            "label": "07: norm2", 
            "time_ms": 0.260992, 
            "time_s": 0.000260992, 
            "timestamp": "1103 15:33:33.595741"
          }, 
          {
            "direction": "backward", 
            "index": 7, 
            "label": "07: norm2", 
            "time_ms": 0.960512, 
            "time_s": 0.0009605120000000001, 
            "timestamp": "1103 15:33:33.595744"
          }, 
          {
            "direction": "forward", 
            "index": 8, 
            "label": "08: pool2", 
            "time_ms": 0.089088, 
            "time_s": 8.9088e-05, 
            "timestamp": "1103 15:33:33.595747"
          }, 
          {
            "direction": "backward", 
            "index": 8, 
            "label": "08: pool2", 
            "time_ms": 0.001696, 
            "time_s": 1.6960000000000002e-06, 
            "timestamp": "1103 15:33:33.595751"
          }, 
          {
            "direction": "forward", 
            "index": 9, 
            "label": "09: conv3", 
            "time_ms": 1.57139, 
            "time_s": 0.0015713900000000002, 
            "timestamp": "1103 15:33:33.595753"
          }, 
          {
            "direction": "backward", 
            "index": 9, 
            "label": "09: conv3", 
            "time_ms": 2.04595, 
            "time_s": 0.00204595, 
            "timestamp": "1103 15:33:33.595757"
          }, 
          {
            "direction": "forward", 
            "index": 10, 
            "label": "10: relu3", 
            "time_ms": 0.02832, 
            "time_s": 2.8320000000000003e-05, 
            "timestamp": "1103 15:33:33.595758"
          }, 
          {
            "direction": "backward", 
            "index": 10, 
            "label": "10: relu3", 
            "time_ms": 0.001952, 
            "time_s": 1.952e-06, 
            "timestamp": "1103 15:33:33.595762"
          }, 
          {
            "direction": "forward", 
            "index": 11, 
            "label": "11: conv4", 
            "time_ms": 2.10637, 
            "time_s": 0.00210637, 
            "timestamp": "1103 15:33:33.595764"
          }, 
          {
            "direction": "backward", 
            "index": 11, 
            "label": "11: conv4", 
            "time_ms": 2.51462, 
            "time_s": 0.00251462, 
            "timestamp": "1103 15:33:33.595767"
          }, 
          {
            "direction": "forward", 
            "index": 12, 
            "label": "12: relu4", 
            "time_ms": 0.028672, 
            "time_s": 2.8672e-05, 
            "timestamp": "1103 15:33:33.595770"
          }, 
          {
            "direction": "backward", 
            "index": 12, 
            "label": "12: relu4", 
            "time_ms": 0.001088, 
            "time_s": 1.088e-06, 
            "timestamp": "1103 15:33:33.595772"
          }, 
          {
            "direction": "forward", 
            "index": 13, 
            "label": "13: conv5", 
            "time_ms": 1.96582, 
            "time_s": 0.00196582, 
            "timestamp": "1103 15:33:33.595775"
          }, 
          {
            "direction": "backward", 
            "index": 13, 
            "label": "13: conv5", 
            "time_ms": 2.04781, 
            "time_s": 0.00204781, 
            "timestamp": "1103 15:33:33.595778"
          }, 
          {
            "direction": "forward", 
            "index": 14, 
            "label": "14: relu5", 
            "time_ms": 0.018432, 
            "time_s": 1.8432000000000002e-05, 
            "timestamp": "1103 15:33:33.595782"
          }, 
          {
            "direction": "backward", 
            "index": 14, 
            "label": "14: relu5", 
            "time_ms": 0.001024, 
            "time_s": 1.024e-06, 
            "timestamp": "1103 15:33:33.595784"
          }, 
          {
            "direction": "forward", 
            "index": 15, 
            "label": "15: pool5", 
            "time_ms": 0.026624, 
            "time_s": 2.6623999999999998e-05, 
            "timestamp": "1103 15:33:33.595788"
          }, 
          {
            "direction": "backward", 
            "index": 15, 
            "label": "15: pool5", 
            "time_ms": 0.002048, 
            "time_s": 2.048e-06, 
            "timestamp": "1103 15:33:33.595789"
          }, 
          {
            "direction": "forward", 
            "index": 16, 
            "label": "16: fc6", 
            "time_ms": 1.28176, 
            "time_s": 0.00128176, 
            "timestamp": "1103 15:33:33.595793"
          }, 
          {
            "direction": "backward", 
            "index": 16, 
            "label": "16: fc6", 
            "time_ms": 2.24768, 
            "time_s": 0.0022476799999999997, 
            "timestamp": "1103 15:33:33.595795"
          }, 
          {
            "direction": "forward", 
            "index": 17, 
            "label": "17: relu6", 
            "time_ms": 0.006144, 
            "time_s": 6.144e-06, 
            "timestamp": "1103 15:33:33.595798"
          }, 
          {
            "direction": "backward", 
            "index": 17, 
            "label": "17: relu6", 
            "time_ms": 0.000992, 
            "time_s": 9.92e-07, 
            "timestamp": "1103 15:33:33.595801"
          }, 
          {
            "direction": "forward", 
            "index": 18, 
            "label": "18: drop6", 
            "time_ms": 0.01616, 
            "time_s": 1.616e-05, 
            "timestamp": "1103 15:33:33.595804"
          }, 
          {
            "direction": "backward", 
            "index": 18, 
            "label": "18: drop6", 
            "time_ms": 0.001696, 
            "time_s": 1.6960000000000002e-06, 
            "timestamp": "1103 15:33:33.595806"
          }, 
          {
            "direction": "forward", 
            "index": 19, 
            "label": "19: fc7", 
            "time_ms": 0.574464, 
            "time_s": 0.000574464, 
            "timestamp": "1103 15:33:33.595809"
          }, 
          {
            "direction": "backward", 
            "index": 19, 
            "label": "19: fc7", 
            "time_ms": 1.1417, 
            "time_s": 0.0011417, 
            "timestamp": "1103 15:33:33.595813"
          }, 
          {
            "direction": "forward", 
            "index": 20, 
            "label": "20: relu7", 
            "time_ms": 0.006048, 
            "time_s": 6.048e-06, 
            "timestamp": "1103 15:33:33.595819"
          }, 
          {
            "direction": "backward", 
            "index": 20, 
            "label": "20: relu7", 
            "time_ms": 0.001728, 
            "time_s": 1.728e-06, 
            "timestamp": "1103 15:33:33.595829"
          }, 
          {
            "direction": "forward", 
            "index": 21, 
            "label": "21: drop7", 
            "time_ms": 0.012864, 
            "time_s": 1.2864e-05, 
            "timestamp": "1103 15:33:33.595831"
          }, 
          {
            "direction": "backward", 
            "index": 21, 
            "label": "21: drop7", 
            "time_ms": 0.001184, 
            "time_s": 1.184e-06, 
            "timestamp": "1103 15:33:33.595834"
          }, 
          {
            "direction": "forward", 
            "index": 22, 
            "label": "22: fc8", 
            "time_ms": 0.145408, 
            "time_s": 0.000145408, 
            "timestamp": "1103 15:33:33.595837"
          }, 
          {
            "direction": "backward", 
            "index": 22, 
            "label": "22: fc8", 
            "time_ms": 0.490496, 
            "time_s": 0.000490496, 
            "timestamp": "1103 15:33:33.595839"
          }, 
          {
            "direction": "forward", 
            "index": 23, 
            "label": "23: prob", 
            "time_ms": 0.135168, 
            "time_s": 0.00013516800000000002, 
            "timestamp": "1103 15:33:33.595842"
          }, 
          {
            "direction": "backward", 
            "index": 23, 
            "label": "23: prob", 
            "time_ms": 0.113664, 
            "time_s": 0.000113664, 
            "timestamp": "1103 15:33:33.595845"
          }
        ], 
        "post_processed": "yes", 
        "repeat": 1, 
        "return_code": 0, 
        "run_success": "yes", 
        "run_success_bool": true, 
        "time_bw_ms": 19.364, 
        "time_bw_s": 0.019364000000000003, 
        "time_fw_ms": 13.0482, 
        "time_fw_s": 0.0130482, 
        "time_fwbw_ms": 32.6134, 
        "time_fwbw_s": 0.0326134, 
        "time_total_ms": 32.6134, 
        "time_total_ms_kernel_0": 32.6134, 
        "time_total_s": 0.0326134, 
        "time_total_s_kernel_0": 0.0326134, 
        "total_execution_time": 0.0
      }
    }
  ], 
  "choices": {
    "cmd_key": "time_gpu", 
    "compile_type": "dynamic", 
    "compiler_flags": {}, 
    "cpu_freq": "max", 
    "data_uoa": "caffe", 
    "dataset_file": "", 
    "device_cfg": {}, 
    "device_id": "", 
    "energy": "no", 
    "env": {
      "CK_CAFFE_BATCH_SIZE": 12, 
      "CK_CAFFE_GPU_ID": 0, 
      "CK_CAFFE_ITERATIONS": 4166, 
      "CK_CAFFE_MODEL": "/home/anton/CK_REPOS/ck-caffe/program/caffe/tmp/tmp-mQzC7h.prototxt", 
      "CK_CPU_FREQUENCY": "max", 
      "CK_GPU_FREQUENCY": "max"
    }, 
    "gpu_freq": "max", 
    "host_os": "linux-64", 
    "module_uoa": "b0ac08fe1d3c2615", 
    "no_state_check": "yes", 
    "repeat": 1, 
    "skip_calibration": "yes", 
    "skip_print_timers": "yes", 
    "target": "", 
    "target_os": "linux-64", 
    "target_os_bits": "64"
  }, 
  "choices_order": [
    "##env#CK_CAFFE_BATCH_SIZE"
  ], 
  "features": {
    "compiler_version": {
      "list": [], 
      "raw": "", 
      "str": ""
    }, 
    "number_of_selected_compiler_flags": 0, 
    "platform": {
      "cpu": {
        "all_freqs": {}, 
        "cpu_abi": "", 
        "cpu_features": "fpu vme de pse tsc msr pae mce cx8 apic sep mtrr pge mca cmov pat pse36 clflush dts acpi mmx fxsr sse sse2 ss ht tm pbe syscall nx pdpe1gb rdtscp lm constant_tsc arch_perfmon pebs bts rep_good nopl xtopology nonstop_tsc aperfmperf eagerfpu pni pclmulqdq dtes64 monitor ds_cpl vmx smx est tm2 ssse3 sdbg fma cx16 xtpr pdcm pcid dca sse4_1 sse4_2 x2apic movbe popcnt tsc_deadline_timer aes xsave avx f16c rdrand lahf_lm abm epb tpr_shadow vnmi flexpriority ept vpid fsgsbase tsc_adjust bmi1 avx2 smep bmi2 erms invpcid cqm xsaveopt cqm_llc cqm_occup_llc dtherm ida arat pln pts", 
        "current_freq": {
          "0": 1200.042, 
          "1": 1200.042, 
          "10": 1211.093, 
          "11": 1558.699, 
          "12": 2209.347, 
          "13": 1299.769, 
          "14": 1700.023, 
          "15": 1201.031, 
          "16": 1509.824, 
          "17": 1498.863, 
          "18": 1273.804, 
          "19": 1201.66, 
          "2": 1556.183, 
          "3": 1242.628, 
          "4": 1688.792, 
          "5": 1232.835, 
          "6": 1397.519, 
          "7": 1411.535, 
          "8": 1251.703, 
          "9": 1199.953
        }, 
        "max_freq": {
          "0": 3000.0, 
          "1": 3000.0, 
          "10": 3000.0, 
          "11": 3000.0, 
          "12": 3000.0, 
          "13": 3000.0, 
          "14": 3000.0, 
          "15": 3000.0, 
          "16": 3000.0, 
          "17": 3000.0, 
          "18": 3000.0, 
          "19": 3000.0, 
          "2": 3000.0, 
          "3": 3000.0, 
          "4": 3000.0, 
          "5": 3000.0, 
          "6": 3000.0, 
          "7": 3000.0, 
          "8": 3000.0, 
          "9": 3000.0
        }, 
        "name": "Intel(R) Xeon(R) CPU E5-2650 v3 @ 2.30GHz", 
        "num_proc": "20", 
        "sub_name": "Intel(R) Xeon(R) CPU E5-2650 v3 @ 2.30GHz", 
        "workload_automation": {
          "device_config": {
            "core_clusters": [
              0, 
              0, 
              0, 
              0, 
              0, 
              0, 
              0, 
              0, 
              0, 
              0, 
              0, 
              0, 
              0, 
              0, 
              0, 
              0, 
              0, 
              0, 
              0, 
              0
            ], 
            "core_names": [
              "Intel(R) Xeon(R) CPU E5-2650 v3 @ 2.30GHz", 
              "Intel(R) Xeon(R) CPU E5-2650 v3 @ 2.30GHz", 
              "Intel(R) Xeon(R) CPU E5-2650 v3 @ 2.30GHz", 
              "Intel(R) Xeon(R) CPU E5-2650 v3 @ 2.30GHz", 
              "Intel(R) Xeon(R) CPU E5-2650 v3 @ 2.30GHz", 
              "Intel(R) Xeon(R) CPU E5-2650 v3 @ 2.30GHz", 
              "Intel(R) Xeon(R) CPU E5-2650 v3 @ 2.30GHz", 
              "Intel(R) Xeon(R) CPU E5-2650 v3 @ 2.30GHz", 
              "Intel(R) Xeon(R) CPU E5-2650 v3 @ 2.30GHz", 
              "Intel(R) Xeon(R) CPU E5-2650 v3 @ 2.30GHz", 
              "Intel(R) Xeon(R) CPU E5-2650 v3 @ 2.30GHz", 
              "Intel(R) Xeon(R) CPU E5-2650 v3 @ 2.30GHz", 
              "Intel(R) Xeon(R) CPU E5-2650 v3 @ 2.30GHz", 
              "Intel(R) Xeon(R) CPU E5-2650 v3 @ 2.30GHz", 
              "Intel(R) Xeon(R) CPU E5-2650 v3 @ 2.30GHz", 
              "Intel(R) Xeon(R) CPU E5-2650 v3 @ 2.30GHz", 
              "Intel(R) Xeon(R) CPU E5-2650 v3 @ 2.30GHz", 
              "Intel(R) Xeon(R) CPU E5-2650 v3 @ 2.30GHz", 
              "Intel(R) Xeon(R) CPU E5-2650 v3 @ 2.30GHz", 
              "Intel(R) Xeon(R) CPU E5-2650 v3 @ 2.30GHz"
            ]
          }
        }
      }, 
      "cpu_misc": {
        "0": {
          "address sizes": "46 bits physical, 48 bits virtual", 
          "apicid": "0", 
          "bogomips": "4589.54", 
          "bugs": "", 
          "cache size": "25600 KB", 
          "cache_alignment": "64", 
          "ck_cpu_name": "Intel(R) Xeon(R) CPU E5-2650 v3 @ 2.30GHz", 
          "ck_cpu_subname": "Intel(R) Xeon(R) CPU E5-2650 v3 @ 2.30GHz", 
          "clflush size": "64", 
          "core id": "0", 
          "cpu MHz": "1200.042", 
          "cpu cores": "10", 
          "cpu family": "6", 
          "cpu_features": "fpu vme de pse tsc msr pae mce cx8 apic sep mtrr pge mca cmov pat pse36 clflush dts acpi mmx fxsr sse sse2 ss ht tm pbe syscall nx pdpe1gb rdtscp lm constant_tsc arch_perfmon pebs bts rep_good nopl xtopology nonstop_tsc aperfmperf eagerfpu pni pclmulqdq dtes64 monitor ds_cpl vmx smx est tm2 ssse3 sdbg fma cx16 xtpr pdcm pcid dca sse4_1 sse4_2 x2apic movbe popcnt tsc_deadline_timer aes xsave avx f16c rdrand lahf_lm abm epb tpr_shadow vnmi flexpriority ept vpid fsgsbase tsc_adjust bmi1 avx2 smep bmi2 erms invpcid cqm xsaveopt cqm_llc cqm_occup_llc dtherm ida arat pln pts", 
          "cpuid level": "15", 
          "cur_freq": 1200.042, 
          "flags": "fpu vme de pse tsc msr pae mce cx8 apic sep mtrr pge mca cmov pat pse36 clflush dts acpi mmx fxsr sse sse2 ss ht tm pbe syscall nx pdpe1gb rdtscp lm constant_tsc arch_perfmon pebs bts rep_good nopl xtopology nonstop_tsc aperfmperf eagerfpu pni pclmulqdq dtes64 monitor ds_cpl vmx smx est tm2 ssse3 sdbg fma cx16 xtpr pdcm pcid dca sse4_1 sse4_2 x2apic movbe popcnt tsc_deadline_timer aes xsave avx f16c rdrand lahf_lm abm epb tpr_shadow vnmi flexpriority ept vpid fsgsbase tsc_adjust bmi1 avx2 smep bmi2 erms invpcid cqm xsaveopt cqm_llc cqm_occup_llc dtherm ida arat pln pts", 
          "fpu": "yes", 
          "fpu_exception": "yes", 
          "initial apicid": "0", 
          "max_freq": 3000.0, 
          "microcode": "0x2e", 
          "model": "63", 
          "model name": "Intel(R) Xeon(R) CPU E5-2650 v3 @ 2.30GHz", 
          "physical id": "0", 
          "power management": "", 
          "processor": "0", 
          "siblings": "20", 
          "stepping": "2", 
          "vendor_id": "GenuineIntel", 
          "wp": "yes"
        }, 
        "1": {
          "address sizes": "46 bits physical, 48 bits virtual", 
          "apicid": "2", 
          "bogomips": "4589.54", 
          "bugs": "", 
          "cache size": "25600 KB", 
          "cache_alignment": "64", 
          "ck_cpu_name": "Intel(R) Xeon(R) CPU E5-2650 v3 @ 2.30GHz", 
          "ck_cpu_subname": "Intel(R) Xeon(R) CPU E5-2650 v3 @ 2.30GHz", 
          "clflush size": "64", 
          "core id": "1", 
          "cpu MHz": "1200.042", 
          "cpu cores": "10", 
          "cpu family": "6", 
          "cpu_features": "fpu vme de pse tsc msr pae mce cx8 apic sep mtrr pge mca cmov pat pse36 clflush dts acpi mmx fxsr sse sse2 ss ht tm pbe syscall nx pdpe1gb rdtscp lm constant_tsc arch_perfmon pebs bts rep_good nopl xtopology nonstop_tsc aperfmperf eagerfpu pni pclmulqdq dtes64 monitor ds_cpl vmx smx est tm2 ssse3 sdbg fma cx16 xtpr pdcm pcid dca sse4_1 sse4_2 x2apic movbe popcnt tsc_deadline_timer aes xsave avx f16c rdrand lahf_lm abm epb tpr_shadow vnmi flexpriority ept vpid fsgsbase tsc_adjust bmi1 avx2 smep bmi2 erms invpcid cqm xsaveopt cqm_llc cqm_occup_llc dtherm ida arat pln pts", 
          "cpuid level": "15", 
          "cur_freq": 1200.042, 
          "flags": "fpu vme de pse tsc msr pae mce cx8 apic sep mtrr pge mca cmov pat pse36 clflush dts acpi mmx fxsr sse sse2 ss ht tm pbe syscall nx pdpe1gb rdtscp lm constant_tsc arch_perfmon pebs bts rep_good nopl xtopology nonstop_tsc aperfmperf eagerfpu pni pclmulqdq dtes64 monitor ds_cpl vmx smx est tm2 ssse3 sdbg fma cx16 xtpr pdcm pcid dca sse4_1 sse4_2 x2apic movbe popcnt tsc_deadline_timer aes xsave avx f16c rdrand lahf_lm abm epb tpr_shadow vnmi flexpriority ept vpid fsgsbase tsc_adjust bmi1 avx2 smep bmi2 erms invpcid cqm xsaveopt cqm_llc cqm_occup_llc dtherm ida arat pln pts", 
          "fpu": "yes", 
          "fpu_exception": "yes", 
          "initial apicid": "2", 
          "max_freq": 3000.0, 
          "microcode": "0x2e", 
          "model": "63", 
          "model name": "Intel(R) Xeon(R) CPU E5-2650 v3 @ 2.30GHz", 
          "physical id": "0", 
          "power management": "", 
          "processor": "1", 
          "siblings": "20", 
          "stepping": "2", 
          "vendor_id": "GenuineIntel", 
          "wp": "yes"
        }, 
        "10": {
          "address sizes": "46 bits physical, 48 bits virtual", 
          "apicid": "1", 
          "bogomips": "4589.54", 
          "bugs": "", 
          "cache size": "25600 KB", 
          "cache_alignment": "64", 
          "ck_cpu_name": "Intel(R) Xeon(R) CPU E5-2650 v3 @ 2.30GHz", 
          "ck_cpu_subname": "Intel(R) Xeon(R) CPU E5-2650 v3 @ 2.30GHz", 
          "clflush size": "64", 
          "core id": "0", 
          "cpu MHz": "1211.093", 
          "cpu cores": "10", 
          "cpu family": "6", 
          "cpu_features": "fpu vme de pse tsc msr pae mce cx8 apic sep mtrr pge mca cmov pat pse36 clflush dts acpi mmx fxsr sse sse2 ss ht tm pbe syscall nx pdpe1gb rdtscp lm constant_tsc arch_perfmon pebs bts rep_good nopl xtopology nonstop_tsc aperfmperf eagerfpu pni pclmulqdq dtes64 monitor ds_cpl vmx smx est tm2 ssse3 sdbg fma cx16 xtpr pdcm pcid dca sse4_1 sse4_2 x2apic movbe popcnt tsc_deadline_timer aes xsave avx f16c rdrand lahf_lm abm epb tpr_shadow vnmi flexpriority ept vpid fsgsbase tsc_adjust bmi1 avx2 smep bmi2 erms invpcid cqm xsaveopt cqm_llc cqm_occup_llc dtherm ida arat pln pts", 
          "cpuid level": "15", 
          "cur_freq": 1211.093, 
          "flags": "fpu vme de pse tsc msr pae mce cx8 apic sep mtrr pge mca cmov pat pse36 clflush dts acpi mmx fxsr sse sse2 ss ht tm pbe syscall nx pdpe1gb rdtscp lm constant_tsc arch_perfmon pebs bts rep_good nopl xtopology nonstop_tsc aperfmperf eagerfpu pni pclmulqdq dtes64 monitor ds_cpl vmx smx est tm2 ssse3 sdbg fma cx16 xtpr pdcm pcid dca sse4_1 sse4_2 x2apic movbe popcnt tsc_deadline_timer aes xsave avx f16c rdrand lahf_lm abm epb tpr_shadow vnmi flexpriority ept vpid fsgsbase tsc_adjust bmi1 avx2 smep bmi2 erms invpcid cqm xsaveopt cqm_llc cqm_occup_llc dtherm ida arat pln pts", 
          "fpu": "yes", 
          "fpu_exception": "yes", 
          "initial apicid": "1", 
          "max_freq": 3000.0, 
          "microcode": "0x2e", 
          "model": "63", 
          "model name": "Intel(R) Xeon(R) CPU E5-2650 v3 @ 2.30GHz", 
          "physical id": "0", 
          "power management": "", 
          "processor": "10", 
          "siblings": "20", 
          "stepping": "2", 
          "vendor_id": "GenuineIntel", 
          "wp": "yes"
        }, 
        "11": {
          "address sizes": "46 bits physical, 48 bits virtual", 
          "apicid": "3", 
          "bogomips": "4589.54", 
          "bugs": "", 
          "cache size": "25600 KB", 
          "cache_alignment": "64", 
          "ck_cpu_name": "Intel(R) Xeon(R) CPU E5-2650 v3 @ 2.30GHz", 
          "ck_cpu_subname": "Intel(R) Xeon(R) CPU E5-2650 v3 @ 2.30GHz", 
          "clflush size": "64", 
          "core id": "1", 
          "cpu MHz": "1558.699", 
          "cpu cores": "10", 
          "cpu family": "6", 
          "cpu_features": "fpu vme de pse tsc msr pae mce cx8 apic sep mtrr pge mca cmov pat pse36 clflush dts acpi mmx fxsr sse sse2 ss ht tm pbe syscall nx pdpe1gb rdtscp lm constant_tsc arch_perfmon pebs bts rep_good nopl xtopology nonstop_tsc aperfmperf eagerfpu pni pclmulqdq dtes64 monitor ds_cpl vmx smx est tm2 ssse3 sdbg fma cx16 xtpr pdcm pcid dca sse4_1 sse4_2 x2apic movbe popcnt tsc_deadline_timer aes xsave avx f16c rdrand lahf_lm abm epb tpr_shadow vnmi flexpriority ept vpid fsgsbase tsc_adjust bmi1 avx2 smep bmi2 erms invpcid cqm xsaveopt cqm_llc cqm_occup_llc dtherm ida arat pln pts", 
          "cpuid level": "15", 
          "cur_freq": 1558.699, 
          "flags": "fpu vme de pse tsc msr pae mce cx8 apic sep mtrr pge mca cmov pat pse36 clflush dts acpi mmx fxsr sse sse2 ss ht tm pbe syscall nx pdpe1gb rdtscp lm constant_tsc arch_perfmon pebs bts rep_good nopl xtopology nonstop_tsc aperfmperf eagerfpu pni pclmulqdq dtes64 monitor ds_cpl vmx smx est tm2 ssse3 sdbg fma cx16 xtpr pdcm pcid dca sse4_1 sse4_2 x2apic movbe popcnt tsc_deadline_timer aes xsave avx f16c rdrand lahf_lm abm epb tpr_shadow vnmi flexpriority ept vpid fsgsbase tsc_adjust bmi1 avx2 smep bmi2 erms invpcid cqm xsaveopt cqm_llc cqm_occup_llc dtherm ida arat pln pts", 
          "fpu": "yes", 
          "fpu_exception": "yes", 
          "initial apicid": "3", 
          "max_freq": 3000.0, 
          "microcode": "0x2e", 
          "model": "63", 
          "model name": "Intel(R) Xeon(R) CPU E5-2650 v3 @ 2.30GHz", 
          "physical id": "0", 
          "power management": "", 
          "processor": "11", 
          "siblings": "20", 
          "stepping": "2", 
          "vendor_id": "GenuineIntel", 
          "wp": "yes"
        }, 
        "12": {
          "address sizes": "46 bits physical, 48 bits virtual", 
          "apicid": "5", 
          "bogomips": "4589.54", 
          "bugs": "", 
          "cache size": "25600 KB", 
          "cache_alignment": "64", 
          "ck_cpu_name": "Intel(R) Xeon(R) CPU E5-2650 v3 @ 2.30GHz", 
          "ck_cpu_subname": "Intel(R) Xeon(R) CPU E5-2650 v3 @ 2.30GHz", 
          "clflush size": "64", 
          "core id": "2", 
          "cpu MHz": "2209.347", 
          "cpu cores": "10", 
          "cpu family": "6", 
          "cpu_features": "fpu vme de pse tsc msr pae mce cx8 apic sep mtrr pge mca cmov pat pse36 clflush dts acpi mmx fxsr sse sse2 ss ht tm pbe syscall nx pdpe1gb rdtscp lm constant_tsc arch_perfmon pebs bts rep_good nopl xtopology nonstop_tsc aperfmperf eagerfpu pni pclmulqdq dtes64 monitor ds_cpl vmx smx est tm2 ssse3 sdbg fma cx16 xtpr pdcm pcid dca sse4_1 sse4_2 x2apic movbe popcnt tsc_deadline_timer aes xsave avx f16c rdrand lahf_lm abm epb tpr_shadow vnmi flexpriority ept vpid fsgsbase tsc_adjust bmi1 avx2 smep bmi2 erms invpcid cqm xsaveopt cqm_llc cqm_occup_llc dtherm ida arat pln pts", 
          "cpuid level": "15", 
          "cur_freq": 2209.347, 
          "flags": "fpu vme de pse tsc msr pae mce cx8 apic sep mtrr pge mca cmov pat pse36 clflush dts acpi mmx fxsr sse sse2 ss ht tm pbe syscall nx pdpe1gb rdtscp lm constant_tsc arch_perfmon pebs bts rep_good nopl xtopology nonstop_tsc aperfmperf eagerfpu pni pclmulqdq dtes64 monitor ds_cpl vmx smx est tm2 ssse3 sdbg fma cx16 xtpr pdcm pcid dca sse4_1 sse4_2 x2apic movbe popcnt tsc_deadline_timer aes xsave avx f16c rdrand lahf_lm abm epb tpr_shadow vnmi flexpriority ept vpid fsgsbase tsc_adjust bmi1 avx2 smep bmi2 erms invpcid cqm xsaveopt cqm_llc cqm_occup_llc dtherm ida arat pln pts", 
          "fpu": "yes", 
          "fpu_exception": "yes", 
          "initial apicid": "5", 
          "max_freq": 3000.0, 
          "microcode": "0x2e", 
          "model": "63", 
          "model name": "Intel(R) Xeon(R) CPU E5-2650 v3 @ 2.30GHz", 
          "physical id": "0", 
          "power management": "", 
          "processor": "12", 
          "siblings": "20", 
          "stepping": "2", 
          "vendor_id": "GenuineIntel", 
          "wp": "yes"
        }, 
        "13": {
          "address sizes": "46 bits physical, 48 bits virtual", 
          "apicid": "7", 
          "bogomips": "4589.54", 
          "bugs": "", 
          "cache size": "25600 KB", 
          "cache_alignment": "64", 
          "ck_cpu_name": "Intel(R) Xeon(R) CPU E5-2650 v3 @ 2.30GHz", 
          "ck_cpu_subname": "Intel(R) Xeon(R) CPU E5-2650 v3 @ 2.30GHz", 
          "clflush size": "64", 
          "core id": "3", 
          "cpu MHz": "1299.769", 
          "cpu cores": "10", 
          "cpu family": "6", 
          "cpu_features": "fpu vme de pse tsc msr pae mce cx8 apic sep mtrr pge mca cmov pat pse36 clflush dts acpi mmx fxsr sse sse2 ss ht tm pbe syscall nx pdpe1gb rdtscp lm constant_tsc arch_perfmon pebs bts rep_good nopl xtopology nonstop_tsc aperfmperf eagerfpu pni pclmulqdq dtes64 monitor ds_cpl vmx smx est tm2 ssse3 sdbg fma cx16 xtpr pdcm pcid dca sse4_1 sse4_2 x2apic movbe popcnt tsc_deadline_timer aes xsave avx f16c rdrand lahf_lm abm epb tpr_shadow vnmi flexpriority ept vpid fsgsbase tsc_adjust bmi1 avx2 smep bmi2 erms invpcid cqm xsaveopt cqm_llc cqm_occup_llc dtherm ida arat pln pts", 
          "cpuid level": "15", 
          "cur_freq": 1299.769, 
          "flags": "fpu vme de pse tsc msr pae mce cx8 apic sep mtrr pge mca cmov pat pse36 clflush dts acpi mmx fxsr sse sse2 ss ht tm pbe syscall nx pdpe1gb rdtscp lm constant_tsc arch_perfmon pebs bts rep_good nopl xtopology nonstop_tsc aperfmperf eagerfpu pni pclmulqdq dtes64 monitor ds_cpl vmx smx est tm2 ssse3 sdbg fma cx16 xtpr pdcm pcid dca sse4_1 sse4_2 x2apic movbe popcnt tsc_deadline_timer aes xsave avx f16c rdrand lahf_lm abm epb tpr_shadow vnmi flexpriority ept vpid fsgsbase tsc_adjust bmi1 avx2 smep bmi2 erms invpcid cqm xsaveopt cqm_llc cqm_occup_llc dtherm ida arat pln pts", 
          "fpu": "yes", 
          "fpu_exception": "yes", 
          "initial apicid": "7", 
          "max_freq": 3000.0, 
          "microcode": "0x2e", 
          "model": "63", 
          "model name": "Intel(R) Xeon(R) CPU E5-2650 v3 @ 2.30GHz", 
          "physical id": "0", 
          "power management": "", 
          "processor": "13", 
          "siblings": "20", 
          "stepping": "2", 
          "vendor_id": "GenuineIntel", 
          "wp": "yes"
        }, 
        "14": {
          "address sizes": "46 bits physical, 48 bits virtual", 
          "apicid": "9", 
          "bogomips": "4589.54", 
          "bugs": "", 
          "cache size": "25600 KB", 
          "cache_alignment": "64", 
          "ck_cpu_name": "Intel(R) Xeon(R) CPU E5-2650 v3 @ 2.30GHz", 
          "ck_cpu_subname": "Intel(R) Xeon(R) CPU E5-2650 v3 @ 2.30GHz", 
          "clflush size": "64", 
          "core id": "4", 
          "cpu MHz": "1700.023", 
          "cpu cores": "10", 
          "cpu family": "6", 
          "cpu_features": "fpu vme de pse tsc msr pae mce cx8 apic sep mtrr pge mca cmov pat pse36 clflush dts acpi mmx fxsr sse sse2 ss ht tm pbe syscall nx pdpe1gb rdtscp lm constant_tsc arch_perfmon pebs bts rep_good nopl xtopology nonstop_tsc aperfmperf eagerfpu pni pclmulqdq dtes64 monitor ds_cpl vmx smx est tm2 ssse3 sdbg fma cx16 xtpr pdcm pcid dca sse4_1 sse4_2 x2apic movbe popcnt tsc_deadline_timer aes xsave avx f16c rdrand lahf_lm abm epb tpr_shadow vnmi flexpriority ept vpid fsgsbase tsc_adjust bmi1 avx2 smep bmi2 erms invpcid cqm xsaveopt cqm_llc cqm_occup_llc dtherm ida arat pln pts", 
          "cpuid level": "15", 
          "cur_freq": 1700.023, 
          "flags": "fpu vme de pse tsc msr pae mce cx8 apic sep mtrr pge mca cmov pat pse36 clflush dts acpi mmx fxsr sse sse2 ss ht tm pbe syscall nx pdpe1gb rdtscp lm constant_tsc arch_perfmon pebs bts rep_good nopl xtopology nonstop_tsc aperfmperf eagerfpu pni pclmulqdq dtes64 monitor ds_cpl vmx smx est tm2 ssse3 sdbg fma cx16 xtpr pdcm pcid dca sse4_1 sse4_2 x2apic movbe popcnt tsc_deadline_timer aes xsave avx f16c rdrand lahf_lm abm epb tpr_shadow vnmi flexpriority ept vpid fsgsbase tsc_adjust bmi1 avx2 smep bmi2 erms invpcid cqm xsaveopt cqm_llc cqm_occup_llc dtherm ida arat pln pts", 
          "fpu": "yes", 
          "fpu_exception": "yes", 
          "initial apicid": "9", 
          "max_freq": 3000.0, 
          "microcode": "0x2e", 
          "model": "63", 
          "model name": "Intel(R) Xeon(R) CPU E5-2650 v3 @ 2.30GHz", 
          "physical id": "0", 
          "power management": "", 
          "processor": "14", 
          "siblings": "20", 
          "stepping": "2", 
          "vendor_id": "GenuineIntel", 
          "wp": "yes"
        }, 
        "15": {
          "address sizes": "46 bits physical, 48 bits virtual", 
          "apicid": "17", 
          "bogomips": "4589.54", 
          "bugs": "", 
          "cache size": "25600 KB", 
          "cache_alignment": "64", 
          "ck_cpu_name": "Intel(R) Xeon(R) CPU E5-2650 v3 @ 2.30GHz", 
          "ck_cpu_subname": "Intel(R) Xeon(R) CPU E5-2650 v3 @ 2.30GHz", 
          "clflush size": "64", 
          "core id": "8", 
          "cpu MHz": "1201.031", 
          "cpu cores": "10", 
          "cpu family": "6", 
          "cpu_features": "fpu vme de pse tsc msr pae mce cx8 apic sep mtrr pge mca cmov pat pse36 clflush dts acpi mmx fxsr sse sse2 ss ht tm pbe syscall nx pdpe1gb rdtscp lm constant_tsc arch_perfmon pebs bts rep_good nopl xtopology nonstop_tsc aperfmperf eagerfpu pni pclmulqdq dtes64 monitor ds_cpl vmx smx est tm2 ssse3 sdbg fma cx16 xtpr pdcm pcid dca sse4_1 sse4_2 x2apic movbe popcnt tsc_deadline_timer aes xsave avx f16c rdrand lahf_lm abm epb tpr_shadow vnmi flexpriority ept vpid fsgsbase tsc_adjust bmi1 avx2 smep bmi2 erms invpcid cqm xsaveopt cqm_llc cqm_occup_llc dtherm ida arat pln pts", 
          "cpuid level": "15", 
          "cur_freq": 1201.031, 
          "flags": "fpu vme de pse tsc msr pae mce cx8 apic sep mtrr pge mca cmov pat pse36 clflush dts acpi mmx fxsr sse sse2 ss ht tm pbe syscall nx pdpe1gb rdtscp lm constant_tsc arch_perfmon pebs bts rep_good nopl xtopology nonstop_tsc aperfmperf eagerfpu pni pclmulqdq dtes64 monitor ds_cpl vmx smx est tm2 ssse3 sdbg fma cx16 xtpr pdcm pcid dca sse4_1 sse4_2 x2apic movbe popcnt tsc_deadline_timer aes xsave avx f16c rdrand lahf_lm abm epb tpr_shadow vnmi flexpriority ept vpid fsgsbase tsc_adjust bmi1 avx2 smep bmi2 erms invpcid cqm xsaveopt cqm_llc cqm_occup_llc dtherm ida arat pln pts", 
          "fpu": "yes", 
          "fpu_exception": "yes", 
          "initial apicid": "17", 
          "max_freq": 3000.0, 
          "microcode": "0x2e", 
          "model": "63", 
          "model name": "Intel(R) Xeon(R) CPU E5-2650 v3 @ 2.30GHz", 
          "physical id": "0", 
          "power management": "", 
          "processor": "15", 
          "siblings": "20", 
          "stepping": "2", 
          "vendor_id": "GenuineIntel", 
          "wp": "yes"
        }, 
        "16": {
          "address sizes": "46 bits physical, 48 bits virtual", 
          "apicid": "19", 
          "bogomips": "4589.54", 
          "bugs": "", 
          "cache size": "25600 KB", 
          "cache_alignment": "64", 
          "ck_cpu_name": "Intel(R) Xeon(R) CPU E5-2650 v3 @ 2.30GHz", 
          "ck_cpu_subname": "Intel(R) Xeon(R) CPU E5-2650 v3 @ 2.30GHz", 
          "clflush size": "64", 
          "core id": "9", 
          "cpu MHz": "1509.824", 
          "cpu cores": "10", 
          "cpu family": "6", 
          "cpu_features": "fpu vme de pse tsc msr pae mce cx8 apic sep mtrr pge mca cmov pat pse36 clflush dts acpi mmx fxsr sse sse2 ss ht tm pbe syscall nx pdpe1gb rdtscp lm constant_tsc arch_perfmon pebs bts rep_good nopl xtopology nonstop_tsc aperfmperf eagerfpu pni pclmulqdq dtes64 monitor ds_cpl vmx smx est tm2 ssse3 sdbg fma cx16 xtpr pdcm pcid dca sse4_1 sse4_2 x2apic movbe popcnt tsc_deadline_timer aes xsave avx f16c rdrand lahf_lm abm epb tpr_shadow vnmi flexpriority ept vpid fsgsbase tsc_adjust bmi1 avx2 smep bmi2 erms invpcid cqm xsaveopt cqm_llc cqm_occup_llc dtherm ida arat pln pts", 
          "cpuid level": "15", 
          "cur_freq": 1509.824, 
          "flags": "fpu vme de pse tsc msr pae mce cx8 apic sep mtrr pge mca cmov pat pse36 clflush dts acpi mmx fxsr sse sse2 ss ht tm pbe syscall nx pdpe1gb rdtscp lm constant_tsc arch_perfmon pebs bts rep_good nopl xtopology nonstop_tsc aperfmperf eagerfpu pni pclmulqdq dtes64 monitor ds_cpl vmx smx est tm2 ssse3 sdbg fma cx16 xtpr pdcm pcid dca sse4_1 sse4_2 x2apic movbe popcnt tsc_deadline_timer aes xsave avx f16c rdrand lahf_lm abm epb tpr_shadow vnmi flexpriority ept vpid fsgsbase tsc_adjust bmi1 avx2 smep bmi2 erms invpcid cqm xsaveopt cqm_llc cqm_occup_llc dtherm ida arat pln pts", 
          "fpu": "yes", 
          "fpu_exception": "yes", 
          "initial apicid": "19", 
          "max_freq": 3000.0, 
          "microcode": "0x2e", 
          "model": "63", 
          "model name": "Intel(R) Xeon(R) CPU E5-2650 v3 @ 2.30GHz", 
          "physical id": "0", 
          "power management": "", 
          "processor": "16", 
          "siblings": "20", 
          "stepping": "2", 
          "vendor_id": "GenuineIntel", 
          "wp": "yes"
        }, 
        "17": {
          "address sizes": "46 bits physical, 48 bits virtual", 
          "apicid": "21", 
          "bogomips": "4589.54", 
          "bugs": "", 
          "cache size": "25600 KB", 
          "cache_alignment": "64", 
          "ck_cpu_name": "Intel(R) Xeon(R) CPU E5-2650 v3 @ 2.30GHz", 
          "ck_cpu_subname": "Intel(R) Xeon(R) CPU E5-2650 v3 @ 2.30GHz", 
          "clflush size": "64", 
          "core id": "10", 
          "cpu MHz": "1396.621", 
          "cpu cores": "10", 
          "cpu family": "6", 
          "cpu_features": "fpu vme de pse tsc msr pae mce cx8 apic sep mtrr pge mca cmov pat pse36 clflush dts acpi mmx fxsr sse sse2 ss ht tm pbe syscall nx pdpe1gb rdtscp lm constant_tsc arch_perfmon pebs bts rep_good nopl xtopology nonstop_tsc aperfmperf eagerfpu pni pclmulqdq dtes64 monitor ds_cpl vmx smx est tm2 ssse3 sdbg fma cx16 xtpr pdcm pcid dca sse4_1 sse4_2 x2apic movbe popcnt tsc_deadline_timer aes xsave avx f16c rdrand lahf_lm abm epb tpr_shadow vnmi flexpriority ept vpid fsgsbase tsc_adjust bmi1 avx2 smep bmi2 erms invpcid cqm xsaveopt cqm_llc cqm_occup_llc dtherm ida arat pln pts", 
          "cpuid level": "15", 
          "cur_freq": 1498.863, 
          "flags": "fpu vme de pse tsc msr pae mce cx8 apic sep mtrr pge mca cmov pat pse36 clflush dts acpi mmx fxsr sse sse2 ss ht tm pbe syscall nx pdpe1gb rdtscp lm constant_tsc arch_perfmon pebs bts rep_good nopl xtopology nonstop_tsc aperfmperf eagerfpu pni pclmulqdq dtes64 monitor ds_cpl vmx smx est tm2 ssse3 sdbg fma cx16 xtpr pdcm pcid dca sse4_1 sse4_2 x2apic movbe popcnt tsc_deadline_timer aes xsave avx f16c rdrand lahf_lm abm epb tpr_shadow vnmi flexpriority ept vpid fsgsbase tsc_adjust bmi1 avx2 smep bmi2 erms invpcid cqm xsaveopt cqm_llc cqm_occup_llc dtherm ida arat pln pts", 
          "fpu": "yes", 
          "fpu_exception": "yes", 
          "initial apicid": "21", 
          "max_freq": 3000.0, 
          "microcode": "0x2e", 
          "model": "63", 
          "model name": "Intel(R) Xeon(R) CPU E5-2650 v3 @ 2.30GHz", 
          "physical id": "0", 
          "power management": "", 
          "processor": "17", 
          "siblings": "20", 
          "stepping": "2", 
          "vendor_id": "GenuineIntel", 
          "wp": "yes"
        }, 
        "18": {
          "address sizes": "46 bits physical, 48 bits virtual", 
          "apicid": "23", 
          "bogomips": "4589.54", 
          "bugs": "", 
          "cache size": "25600 KB", 
          "cache_alignment": "64", 
          "ck_cpu_name": "Intel(R) Xeon(R) CPU E5-2650 v3 @ 2.30GHz", 
          "ck_cpu_subname": "Intel(R) Xeon(R) CPU E5-2650 v3 @ 2.30GHz", 
          "clflush size": "64", 
          "core id": "11", 
          "cpu MHz": "1219.359", 
          "cpu cores": "10", 
          "cpu family": "6", 
          "cpu_features": "fpu vme de pse tsc msr pae mce cx8 apic sep mtrr pge mca cmov pat pse36 clflush dts acpi mmx fxsr sse sse2 ss ht tm pbe syscall nx pdpe1gb rdtscp lm constant_tsc arch_perfmon pebs bts rep_good nopl xtopology nonstop_tsc aperfmperf eagerfpu pni pclmulqdq dtes64 monitor ds_cpl vmx smx est tm2 ssse3 sdbg fma cx16 xtpr pdcm pcid dca sse4_1 sse4_2 x2apic movbe popcnt tsc_deadline_timer aes xsave avx f16c rdrand lahf_lm abm epb tpr_shadow vnmi flexpriority ept vpid fsgsbase tsc_adjust bmi1 avx2 smep bmi2 erms invpcid cqm xsaveopt cqm_llc cqm_occup_llc dtherm ida arat pln pts", 
          "cpuid level": "15", 
          "cur_freq": 1273.804, 
          "flags": "fpu vme de pse tsc msr pae mce cx8 apic sep mtrr pge mca cmov pat pse36 clflush dts acpi mmx fxsr sse sse2 ss ht tm pbe syscall nx pdpe1gb rdtscp lm constant_tsc arch_perfmon pebs bts rep_good nopl xtopology nonstop_tsc aperfmperf eagerfpu pni pclmulqdq dtes64 monitor ds_cpl vmx smx est tm2 ssse3 sdbg fma cx16 xtpr pdcm pcid dca sse4_1 sse4_2 x2apic movbe popcnt tsc_deadline_timer aes xsave avx f16c rdrand lahf_lm abm epb tpr_shadow vnmi flexpriority ept vpid fsgsbase tsc_adjust bmi1 avx2 smep bmi2 erms invpcid cqm xsaveopt cqm_llc cqm_occup_llc dtherm ida arat pln pts", 
          "fpu": "yes", 
          "fpu_exception": "yes", 
          "initial apicid": "23", 
          "max_freq": 3000.0, 
          "microcode": "0x2e", 
          "model": "63", 
          "model name": "Intel(R) Xeon(R) CPU E5-2650 v3 @ 2.30GHz", 
          "physical id": "0", 
          "power management": "", 
          "processor": "18", 
          "siblings": "20", 
          "stepping": "2", 
          "vendor_id": "GenuineIntel", 
          "wp": "yes"
        }, 
        "19": {
          "address sizes": "46 bits physical, 48 bits virtual", 
          "apicid": "25", 
          "bogomips": "4589.54", 
          "bugs": "", 
          "cache size": "25600 KB", 
          "cache_alignment": "64", 
          "ck_cpu_name": "Intel(R) Xeon(R) CPU E5-2650 v3 @ 2.30GHz", 
          "ck_cpu_subname": "Intel(R) Xeon(R) CPU E5-2650 v3 @ 2.30GHz", 
          "clflush size": "64", 
          "core id": "12", 
          "cpu MHz": "1201.660", 
          "cpu cores": "10", 
          "cpu family": "6", 
          "cpu_features": "fpu vme de pse tsc msr pae mce cx8 apic sep mtrr pge mca cmov pat pse36 clflush dts acpi mmx fxsr sse sse2 ss ht tm pbe syscall nx pdpe1gb rdtscp lm constant_tsc arch_perfmon pebs bts rep_good nopl xtopology nonstop_tsc aperfmperf eagerfpu pni pclmulqdq dtes64 monitor ds_cpl vmx smx est tm2 ssse3 sdbg fma cx16 xtpr pdcm pcid dca sse4_1 sse4_2 x2apic movbe popcnt tsc_deadline_timer aes xsave avx f16c rdrand lahf_lm abm epb tpr_shadow vnmi flexpriority ept vpid fsgsbase tsc_adjust bmi1 avx2 smep bmi2 erms invpcid cqm xsaveopt cqm_llc cqm_occup_llc dtherm ida arat pln pts", 
          "cpuid level": "15", 
          "cur_freq": 1201.66, 
          "flags": "fpu vme de pse tsc msr pae mce cx8 apic sep mtrr pge mca cmov pat pse36 clflush dts acpi mmx fxsr sse sse2 ss ht tm pbe syscall nx pdpe1gb rdtscp lm constant_tsc arch_perfmon pebs bts rep_good nopl xtopology nonstop_tsc aperfmperf eagerfpu pni pclmulqdq dtes64 monitor ds_cpl vmx smx est tm2 ssse3 sdbg fma cx16 xtpr pdcm pcid dca sse4_1 sse4_2 x2apic movbe popcnt tsc_deadline_timer aes xsave avx f16c rdrand lahf_lm abm epb tpr_shadow vnmi flexpriority ept vpid fsgsbase tsc_adjust bmi1 avx2 smep bmi2 erms invpcid cqm xsaveopt cqm_llc cqm_occup_llc dtherm ida arat pln pts", 
          "fpu": "yes", 
          "fpu_exception": "yes", 
          "initial apicid": "25", 
          "max_freq": 3000.0, 
          "microcode": "0x2e", 
          "model": "63", 
          "model name": "Intel(R) Xeon(R) CPU E5-2650 v3 @ 2.30GHz", 
          "physical id": "0", 
          "power management": "", 
          "processor": "19", 
          "siblings": "20", 
          "stepping": "2", 
          "vendor_id": "GenuineIntel", 
          "wp": "yes"
        }, 
        "2": {
          "address sizes": "46 bits physical, 48 bits virtual", 
          "apicid": "4", 
          "bogomips": "4589.54", 
          "bugs": "", 
          "cache size": "25600 KB", 
          "cache_alignment": "64", 
          "ck_cpu_name": "Intel(R) Xeon(R) CPU E5-2650 v3 @ 2.30GHz", 
          "ck_cpu_subname": "Intel(R) Xeon(R) CPU E5-2650 v3 @ 2.30GHz", 
          "clflush size": "64", 
          "core id": "2", 
          "cpu MHz": "1556.183", 
          "cpu cores": "10", 
          "cpu family": "6", 
          "cpu_features": "fpu vme de pse tsc msr pae mce cx8 apic sep mtrr pge mca cmov pat pse36 clflush dts acpi mmx fxsr sse sse2 ss ht tm pbe syscall nx pdpe1gb rdtscp lm constant_tsc arch_perfmon pebs bts rep_good nopl xtopology nonstop_tsc aperfmperf eagerfpu pni pclmulqdq dtes64 monitor ds_cpl vmx smx est tm2 ssse3 sdbg fma cx16 xtpr pdcm pcid dca sse4_1 sse4_2 x2apic movbe popcnt tsc_deadline_timer aes xsave avx f16c rdrand lahf_lm abm epb tpr_shadow vnmi flexpriority ept vpid fsgsbase tsc_adjust bmi1 avx2 smep bmi2 erms invpcid cqm xsaveopt cqm_llc cqm_occup_llc dtherm ida arat pln pts", 
          "cpuid level": "15", 
          "cur_freq": 1556.183, 
          "flags": "fpu vme de pse tsc msr pae mce cx8 apic sep mtrr pge mca cmov pat pse36 clflush dts acpi mmx fxsr sse sse2 ss ht tm pbe syscall nx pdpe1gb rdtscp lm constant_tsc arch_perfmon pebs bts rep_good nopl xtopology nonstop_tsc aperfmperf eagerfpu pni pclmulqdq dtes64 monitor ds_cpl vmx smx est tm2 ssse3 sdbg fma cx16 xtpr pdcm pcid dca sse4_1 sse4_2 x2apic movbe popcnt tsc_deadline_timer aes xsave avx f16c rdrand lahf_lm abm epb tpr_shadow vnmi flexpriority ept vpid fsgsbase tsc_adjust bmi1 avx2 smep bmi2 erms invpcid cqm xsaveopt cqm_llc cqm_occup_llc dtherm ida arat pln pts", 
          "fpu": "yes", 
          "fpu_exception": "yes", 
          "initial apicid": "4", 
          "max_freq": 3000.0, 
          "microcode": "0x2e", 
          "model": "63", 
          "model name": "Intel(R) Xeon(R) CPU E5-2650 v3 @ 2.30GHz", 
          "physical id": "0", 
          "power management": "", 
          "processor": "2", 
          "siblings": "20", 
          "stepping": "2", 
          "vendor_id": "GenuineIntel", 
          "wp": "yes"
        }, 
        "3": {
          "address sizes": "46 bits physical, 48 bits virtual", 
          "apicid": "6", 
          "bogomips": "4589.54", 
          "bugs": "", 
          "cache size": "25600 KB", 
          "cache_alignment": "64", 
          "ck_cpu_name": "Intel(R) Xeon(R) CPU E5-2650 v3 @ 2.30GHz", 
          "ck_cpu_subname": "Intel(R) Xeon(R) CPU E5-2650 v3 @ 2.30GHz", 
          "clflush size": "64", 
          "core id": "3", 
          "cpu MHz": "1242.628", 
          "cpu cores": "10", 
          "cpu family": "6", 
          "cpu_features": "fpu vme de pse tsc msr pae mce cx8 apic sep mtrr pge mca cmov pat pse36 clflush dts acpi mmx fxsr sse sse2 ss ht tm pbe syscall nx pdpe1gb rdtscp lm constant_tsc arch_perfmon pebs bts rep_good nopl xtopology nonstop_tsc aperfmperf eagerfpu pni pclmulqdq dtes64 monitor ds_cpl vmx smx est tm2 ssse3 sdbg fma cx16 xtpr pdcm pcid dca sse4_1 sse4_2 x2apic movbe popcnt tsc_deadline_timer aes xsave avx f16c rdrand lahf_lm abm epb tpr_shadow vnmi flexpriority ept vpid fsgsbase tsc_adjust bmi1 avx2 smep bmi2 erms invpcid cqm xsaveopt cqm_llc cqm_occup_llc dtherm ida arat pln pts", 
          "cpuid level": "15", 
          "cur_freq": 1242.628, 
          "flags": "fpu vme de pse tsc msr pae mce cx8 apic sep mtrr pge mca cmov pat pse36 clflush dts acpi mmx fxsr sse sse2 ss ht tm pbe syscall nx pdpe1gb rdtscp lm constant_tsc arch_perfmon pebs bts rep_good nopl xtopology nonstop_tsc aperfmperf eagerfpu pni pclmulqdq dtes64 monitor ds_cpl vmx smx est tm2 ssse3 sdbg fma cx16 xtpr pdcm pcid dca sse4_1 sse4_2 x2apic movbe popcnt tsc_deadline_timer aes xsave avx f16c rdrand lahf_lm abm epb tpr_shadow vnmi flexpriority ept vpid fsgsbase tsc_adjust bmi1 avx2 smep bmi2 erms invpcid cqm xsaveopt cqm_llc cqm_occup_llc dtherm ida arat pln pts", 
          "fpu": "yes", 
          "fpu_exception": "yes", 
          "initial apicid": "6", 
          "max_freq": 3000.0, 
          "microcode": "0x2e", 
          "model": "63", 
          "model name": "Intel(R) Xeon(R) CPU E5-2650 v3 @ 2.30GHz", 
          "physical id": "0", 
          "power management": "", 
          "processor": "3", 
          "siblings": "20", 
          "stepping": "2", 
          "vendor_id": "GenuineIntel", 
          "wp": "yes"
        }, 
        "4": {
          "address sizes": "46 bits physical, 48 bits virtual", 
          "apicid": "8", 
          "bogomips": "4589.54", 
          "bugs": "", 
          "cache size": "25600 KB", 
          "cache_alignment": "64", 
          "ck_cpu_name": "Intel(R) Xeon(R) CPU E5-2650 v3 @ 2.30GHz", 
          "ck_cpu_subname": "Intel(R) Xeon(R) CPU E5-2650 v3 @ 2.30GHz", 
          "clflush size": "64", 
          "core id": "4", 
          "cpu MHz": "1688.792", 
          "cpu cores": "10", 
          "cpu family": "6", 
          "cpu_features": "fpu vme de pse tsc msr pae mce cx8 apic sep mtrr pge mca cmov pat pse36 clflush dts acpi mmx fxsr sse sse2 ss ht tm pbe syscall nx pdpe1gb rdtscp lm constant_tsc arch_perfmon pebs bts rep_good nopl xtopology nonstop_tsc aperfmperf eagerfpu pni pclmulqdq dtes64 monitor ds_cpl vmx smx est tm2 ssse3 sdbg fma cx16 xtpr pdcm pcid dca sse4_1 sse4_2 x2apic movbe popcnt tsc_deadline_timer aes xsave avx f16c rdrand lahf_lm abm epb tpr_shadow vnmi flexpriority ept vpid fsgsbase tsc_adjust bmi1 avx2 smep bmi2 erms invpcid cqm xsaveopt cqm_llc cqm_occup_llc dtherm ida arat pln pts", 
          "cpuid level": "15", 
          "cur_freq": 1688.792, 
          "flags": "fpu vme de pse tsc msr pae mce cx8 apic sep mtrr pge mca cmov pat pse36 clflush dts acpi mmx fxsr sse sse2 ss ht tm pbe syscall nx pdpe1gb rdtscp lm constant_tsc arch_perfmon pebs bts rep_good nopl xtopology nonstop_tsc aperfmperf eagerfpu pni pclmulqdq dtes64 monitor ds_cpl vmx smx est tm2 ssse3 sdbg fma cx16 xtpr pdcm pcid dca sse4_1 sse4_2 x2apic movbe popcnt tsc_deadline_timer aes xsave avx f16c rdrand lahf_lm abm epb tpr_shadow vnmi flexpriority ept vpid fsgsbase tsc_adjust bmi1 avx2 smep bmi2 erms invpcid cqm xsaveopt cqm_llc cqm_occup_llc dtherm ida arat pln pts", 
          "fpu": "yes", 
          "fpu_exception": "yes", 
          "initial apicid": "8", 
          "max_freq": 3000.0, 
          "microcode": "0x2e", 
          "model": "63", 
          "model name": "Intel(R) Xeon(R) CPU E5-2650 v3 @ 2.30GHz", 
          "physical id": "0", 
          "power management": "", 
          "processor": "4", 
          "siblings": "20", 
          "stepping": "2", 
          "vendor_id": "GenuineIntel", 
          "wp": "yes"
        }, 
        "5": {
          "address sizes": "46 bits physical, 48 bits virtual", 
          "apicid": "16", 
          "bogomips": "4589.54", 
          "bugs": "", 
          "cache size": "25600 KB", 
          "cache_alignment": "64", 
          "ck_cpu_name": "Intel(R) Xeon(R) CPU E5-2650 v3 @ 2.30GHz", 
          "ck_cpu_subname": "Intel(R) Xeon(R) CPU E5-2650 v3 @ 2.30GHz", 
          "clflush size": "64", 
          "core id": "8", 
          "cpu MHz": "1232.835", 
          "cpu cores": "10", 
          "cpu family": "6", 
          "cpu_features": "fpu vme de pse tsc msr pae mce cx8 apic sep mtrr pge mca cmov pat pse36 clflush dts acpi mmx fxsr sse sse2 ss ht tm pbe syscall nx pdpe1gb rdtscp lm constant_tsc arch_perfmon pebs bts rep_good nopl xtopology nonstop_tsc aperfmperf eagerfpu pni pclmulqdq dtes64 monitor ds_cpl vmx smx est tm2 ssse3 sdbg fma cx16 xtpr pdcm pcid dca sse4_1 sse4_2 x2apic movbe popcnt tsc_deadline_timer aes xsave avx f16c rdrand lahf_lm abm epb tpr_shadow vnmi flexpriority ept vpid fsgsbase tsc_adjust bmi1 avx2 smep bmi2 erms invpcid cqm xsaveopt cqm_llc cqm_occup_llc dtherm ida arat pln pts", 
          "cpuid level": "15", 
          "cur_freq": 1232.835, 
          "flags": "fpu vme de pse tsc msr pae mce cx8 apic sep mtrr pge mca cmov pat pse36 clflush dts acpi mmx fxsr sse sse2 ss ht tm pbe syscall nx pdpe1gb rdtscp lm constant_tsc arch_perfmon pebs bts rep_good nopl xtopology nonstop_tsc aperfmperf eagerfpu pni pclmulqdq dtes64 monitor ds_cpl vmx smx est tm2 ssse3 sdbg fma cx16 xtpr pdcm pcid dca sse4_1 sse4_2 x2apic movbe popcnt tsc_deadline_timer aes xsave avx f16c rdrand lahf_lm abm epb tpr_shadow vnmi flexpriority ept vpid fsgsbase tsc_adjust bmi1 avx2 smep bmi2 erms invpcid cqm xsaveopt cqm_llc cqm_occup_llc dtherm ida arat pln pts", 
          "fpu": "yes", 
          "fpu_exception": "yes", 
          "initial apicid": "16", 
          "max_freq": 3000.0, 
          "microcode": "0x2e", 
          "model": "63", 
          "model name": "Intel(R) Xeon(R) CPU E5-2650 v3 @ 2.30GHz", 
          "physical id": "0", 
          "power management": "", 
          "processor": "5", 
          "siblings": "20", 
          "stepping": "2", 
          "vendor_id": "GenuineIntel", 
          "wp": "yes"
        }, 
        "6": {
          "address sizes": "46 bits physical, 48 bits virtual", 
          "apicid": "18", 
          "bogomips": "4589.54", 
          "bugs": "", 
          "cache size": "25600 KB", 
          "cache_alignment": "64", 
          "ck_cpu_name": "Intel(R) Xeon(R) CPU E5-2650 v3 @ 2.30GHz", 
          "ck_cpu_subname": "Intel(R) Xeon(R) CPU E5-2650 v3 @ 2.30GHz", 
          "clflush size": "64", 
          "core id": "9", 
          "cpu MHz": "1397.519", 
          "cpu cores": "10", 
          "cpu family": "6", 
          "cpu_features": "fpu vme de pse tsc msr pae mce cx8 apic sep mtrr pge mca cmov pat pse36 clflush dts acpi mmx fxsr sse sse2 ss ht tm pbe syscall nx pdpe1gb rdtscp lm constant_tsc arch_perfmon pebs bts rep_good nopl xtopology nonstop_tsc aperfmperf eagerfpu pni pclmulqdq dtes64 monitor ds_cpl vmx smx est tm2 ssse3 sdbg fma cx16 xtpr pdcm pcid dca sse4_1 sse4_2 x2apic movbe popcnt tsc_deadline_timer aes xsave avx f16c rdrand lahf_lm abm epb tpr_shadow vnmi flexpriority ept vpid fsgsbase tsc_adjust bmi1 avx2 smep bmi2 erms invpcid cqm xsaveopt cqm_llc cqm_occup_llc dtherm ida arat pln pts", 
          "cpuid level": "15", 
          "cur_freq": 1397.519, 
          "flags": "fpu vme de pse tsc msr pae mce cx8 apic sep mtrr pge mca cmov pat pse36 clflush dts acpi mmx fxsr sse sse2 ss ht tm pbe syscall nx pdpe1gb rdtscp lm constant_tsc arch_perfmon pebs bts rep_good nopl xtopology nonstop_tsc aperfmperf eagerfpu pni pclmulqdq dtes64 monitor ds_cpl vmx smx est tm2 ssse3 sdbg fma cx16 xtpr pdcm pcid dca sse4_1 sse4_2 x2apic movbe popcnt tsc_deadline_timer aes xsave avx f16c rdrand lahf_lm abm epb tpr_shadow vnmi flexpriority ept vpid fsgsbase tsc_adjust bmi1 avx2 smep bmi2 erms invpcid cqm xsaveopt cqm_llc cqm_occup_llc dtherm ida arat pln pts", 
          "fpu": "yes", 
          "fpu_exception": "yes", 
          "initial apicid": "18", 
          "max_freq": 3000.0, 
          "microcode": "0x2e", 
          "model": "63", 
          "model name": "Intel(R) Xeon(R) CPU E5-2650 v3 @ 2.30GHz", 
          "physical id": "0", 
          "power management": "", 
          "processor": "6", 
          "siblings": "20", 
          "stepping": "2", 
          "vendor_id": "GenuineIntel", 
          "wp": "yes"
        }, 
        "7": {
          "address sizes": "46 bits physical, 48 bits virtual", 
          "apicid": "20", 
          "bogomips": "4589.54", 
          "bugs": "", 
          "cache size": "25600 KB", 
          "cache_alignment": "64", 
          "ck_cpu_name": "Intel(R) Xeon(R) CPU E5-2650 v3 @ 2.30GHz", 
          "ck_cpu_subname": "Intel(R) Xeon(R) CPU E5-2650 v3 @ 2.30GHz", 
          "clflush size": "64", 
          "core id": "10", 
          "cpu MHz": "1411.535", 
          "cpu cores": "10", 
          "cpu family": "6", 
          "cpu_features": "fpu vme de pse tsc msr pae mce cx8 apic sep mtrr pge mca cmov pat pse36 clflush dts acpi mmx fxsr sse sse2 ss ht tm pbe syscall nx pdpe1gb rdtscp lm constant_tsc arch_perfmon pebs bts rep_good nopl xtopology nonstop_tsc aperfmperf eagerfpu pni pclmulqdq dtes64 monitor ds_cpl vmx smx est tm2 ssse3 sdbg fma cx16 xtpr pdcm pcid dca sse4_1 sse4_2 x2apic movbe popcnt tsc_deadline_timer aes xsave avx f16c rdrand lahf_lm abm epb tpr_shadow vnmi flexpriority ept vpid fsgsbase tsc_adjust bmi1 avx2 smep bmi2 erms invpcid cqm xsaveopt cqm_llc cqm_occup_llc dtherm ida arat pln pts", 
          "cpuid level": "15", 
          "cur_freq": 1411.535, 
          "flags": "fpu vme de pse tsc msr pae mce cx8 apic sep mtrr pge mca cmov pat pse36 clflush dts acpi mmx fxsr sse sse2 ss ht tm pbe syscall nx pdpe1gb rdtscp lm constant_tsc arch_perfmon pebs bts rep_good nopl xtopology nonstop_tsc aperfmperf eagerfpu pni pclmulqdq dtes64 monitor ds_cpl vmx smx est tm2 ssse3 sdbg fma cx16 xtpr pdcm pcid dca sse4_1 sse4_2 x2apic movbe popcnt tsc_deadline_timer aes xsave avx f16c rdrand lahf_lm abm epb tpr_shadow vnmi flexpriority ept vpid fsgsbase tsc_adjust bmi1 avx2 smep bmi2 erms invpcid cqm xsaveopt cqm_llc cqm_occup_llc dtherm ida arat pln pts", 
          "fpu": "yes", 
          "fpu_exception": "yes", 
          "initial apicid": "20", 
          "max_freq": 3000.0, 
          "microcode": "0x2e", 
          "model": "63", 
          "model name": "Intel(R) Xeon(R) CPU E5-2650 v3 @ 2.30GHz", 
          "physical id": "0", 
          "power management": "", 
          "processor": "7", 
          "siblings": "20", 
          "stepping": "2", 
          "vendor_id": "GenuineIntel", 
          "wp": "yes"
        }, 
        "8": {
          "address sizes": "46 bits physical, 48 bits virtual", 
          "apicid": "22", 
          "bogomips": "4589.54", 
          "bugs": "", 
          "cache size": "25600 KB", 
          "cache_alignment": "64", 
          "ck_cpu_name": "Intel(R) Xeon(R) CPU E5-2650 v3 @ 2.30GHz", 
          "ck_cpu_subname": "Intel(R) Xeon(R) CPU E5-2650 v3 @ 2.30GHz", 
          "clflush size": "64", 
          "core id": "11", 
          "cpu MHz": "1251.703", 
          "cpu cores": "10", 
          "cpu family": "6", 
          "cpu_features": "fpu vme de pse tsc msr pae mce cx8 apic sep mtrr pge mca cmov pat pse36 clflush dts acpi mmx fxsr sse sse2 ss ht tm pbe syscall nx pdpe1gb rdtscp lm constant_tsc arch_perfmon pebs bts rep_good nopl xtopology nonstop_tsc aperfmperf eagerfpu pni pclmulqdq dtes64 monitor ds_cpl vmx smx est tm2 ssse3 sdbg fma cx16 xtpr pdcm pcid dca sse4_1 sse4_2 x2apic movbe popcnt tsc_deadline_timer aes xsave avx f16c rdrand lahf_lm abm epb tpr_shadow vnmi flexpriority ept vpid fsgsbase tsc_adjust bmi1 avx2 smep bmi2 erms invpcid cqm xsaveopt cqm_llc cqm_occup_llc dtherm ida arat pln pts", 
          "cpuid level": "15", 
          "cur_freq": 1251.703, 
          "flags": "fpu vme de pse tsc msr pae mce cx8 apic sep mtrr pge mca cmov pat pse36 clflush dts acpi mmx fxsr sse sse2 ss ht tm pbe syscall nx pdpe1gb rdtscp lm constant_tsc arch_perfmon pebs bts rep_good nopl xtopology nonstop_tsc aperfmperf eagerfpu pni pclmulqdq dtes64 monitor ds_cpl vmx smx est tm2 ssse3 sdbg fma cx16 xtpr pdcm pcid dca sse4_1 sse4_2 x2apic movbe popcnt tsc_deadline_timer aes xsave avx f16c rdrand lahf_lm abm epb tpr_shadow vnmi flexpriority ept vpid fsgsbase tsc_adjust bmi1 avx2 smep bmi2 erms invpcid cqm xsaveopt cqm_llc cqm_occup_llc dtherm ida arat pln pts", 
          "fpu": "yes", 
          "fpu_exception": "yes", 
          "initial apicid": "22", 
          "max_freq": 3000.0, 
          "microcode": "0x2e", 
          "model": "63", 
          "model name": "Intel(R) Xeon(R) CPU E5-2650 v3 @ 2.30GHz", 
          "physical id": "0", 
          "power management": "", 
          "processor": "8", 
          "siblings": "20", 
          "stepping": "2", 
          "vendor_id": "GenuineIntel", 
          "wp": "yes"
        }, 
        "9": {
          "address sizes": "46 bits physical, 48 bits virtual", 
          "apicid": "24", 
          "bogomips": "4589.54", 
          "bugs": "", 
          "cache size": "25600 KB", 
          "cache_alignment": "64", 
          "ck_cpu_name": "Intel(R) Xeon(R) CPU E5-2650 v3 @ 2.30GHz", 
          "ck_cpu_subname": "Intel(R) Xeon(R) CPU E5-2650 v3 @ 2.30GHz", 
          "clflush size": "64", 
          "core id": "12", 
          "cpu MHz": "1199.953", 
          "cpu cores": "10", 
          "cpu family": "6", 
          "cpu_features": "fpu vme de pse tsc msr pae mce cx8 apic sep mtrr pge mca cmov pat pse36 clflush dts acpi mmx fxsr sse sse2 ss ht tm pbe syscall nx pdpe1gb rdtscp lm constant_tsc arch_perfmon pebs bts rep_good nopl xtopology nonstop_tsc aperfmperf eagerfpu pni pclmulqdq dtes64 monitor ds_cpl vmx smx est tm2 ssse3 sdbg fma cx16 xtpr pdcm pcid dca sse4_1 sse4_2 x2apic movbe popcnt tsc_deadline_timer aes xsave avx f16c rdrand lahf_lm abm epb tpr_shadow vnmi flexpriority ept vpid fsgsbase tsc_adjust bmi1 avx2 smep bmi2 erms invpcid cqm xsaveopt cqm_llc cqm_occup_llc dtherm ida arat pln pts", 
          "cpuid level": "15", 
          "cur_freq": 1199.953, 
          "flags": "fpu vme de pse tsc msr pae mce cx8 apic sep mtrr pge mca cmov pat pse36 clflush dts acpi mmx fxsr sse sse2 ss ht tm pbe syscall nx pdpe1gb rdtscp lm constant_tsc arch_perfmon pebs bts rep_good nopl xtopology nonstop_tsc aperfmperf eagerfpu pni pclmulqdq dtes64 monitor ds_cpl vmx smx est tm2 ssse3 sdbg fma cx16 xtpr pdcm pcid dca sse4_1 sse4_2 x2apic movbe popcnt tsc_deadline_timer aes xsave avx f16c rdrand lahf_lm abm epb tpr_shadow vnmi flexpriority ept vpid fsgsbase tsc_adjust bmi1 avx2 smep bmi2 erms invpcid cqm xsaveopt cqm_llc cqm_occup_llc dtherm ida arat pln pts", 
          "fpu": "yes", 
          "fpu_exception": "yes", 
          "initial apicid": "24", 
          "max_freq": 3000.0, 
          "microcode": "0x2e", 
          "model": "63", 
          "model name": "Intel(R) Xeon(R) CPU E5-2650 v3 @ 2.30GHz", 
          "physical id": "0", 
          "power management": "", 
          "processor": "9", 
          "siblings": "20", 
          "stepping": "2", 
          "vendor_id": "GenuineIntel", 
          "wp": "yes"
        }
      }, 
      "cpu_new_format": "", 
      "cpu_unique": [
        {
          "address sizes": "46 bits physical, 48 bits virtual", 
          "apicid": "0", 
          "bogomips": "4589.54", 
          "bugs": "", 
          "cache size": "25600 KB", 
          "cache_alignment": "64", 
          "ck_cpu_name": "Intel(R) Xeon(R) CPU E5-2650 v3 @ 2.30GHz", 
          "ck_cpu_subname": "Intel(R) Xeon(R) CPU E5-2650 v3 @ 2.30GHz", 
          "clflush size": "64", 
          "core id": "0", 
          "cpu MHz": "1200.042", 
          "cpu cores": "10", 
          "cpu family": "6", 
          "cpu_features": "fpu vme de pse tsc msr pae mce cx8 apic sep mtrr pge mca cmov pat pse36 clflush dts acpi mmx fxsr sse sse2 ss ht tm pbe syscall nx pdpe1gb rdtscp lm constant_tsc arch_perfmon pebs bts rep_good nopl xtopology nonstop_tsc aperfmperf eagerfpu pni pclmulqdq dtes64 monitor ds_cpl vmx smx est tm2 ssse3 sdbg fma cx16 xtpr pdcm pcid dca sse4_1 sse4_2 x2apic movbe popcnt tsc_deadline_timer aes xsave avx f16c rdrand lahf_lm abm epb tpr_shadow vnmi flexpriority ept vpid fsgsbase tsc_adjust bmi1 avx2 smep bmi2 erms invpcid cqm xsaveopt cqm_llc cqm_occup_llc dtherm ida arat pln pts", 
          "cpuid level": "15", 
          "cur_freq": 1200.042, 
          "flags": "fpu vme de pse tsc msr pae mce cx8 apic sep mtrr pge mca cmov pat pse36 clflush dts acpi mmx fxsr sse sse2 ss ht tm pbe syscall nx pdpe1gb rdtscp lm constant_tsc arch_perfmon pebs bts rep_good nopl xtopology nonstop_tsc aperfmperf eagerfpu pni pclmulqdq dtes64 monitor ds_cpl vmx smx est tm2 ssse3 sdbg fma cx16 xtpr pdcm pcid dca sse4_1 sse4_2 x2apic movbe popcnt tsc_deadline_timer aes xsave avx f16c rdrand lahf_lm abm epb tpr_shadow vnmi flexpriority ept vpid fsgsbase tsc_adjust bmi1 avx2 smep bmi2 erms invpcid cqm xsaveopt cqm_llc cqm_occup_llc dtherm ida arat pln pts", 
          "fpu": "yes", 
          "fpu_exception": "yes", 
          "initial apicid": "0", 
          "max_freq": 3000.0, 
          "microcode": "0x2e", 
          "model": "63", 
          "model name": "Intel(R) Xeon(R) CPU E5-2650 v3 @ 2.30GHz", 
          "physical id": "0", 
          "power management": "", 
          "processor": "0", 
          "siblings": "20", 
          "stepping": "2", 
          "vendor_id": "GenuineIntel", 
          "wp": "yes"
        }
      ], 
      "gpu": {
        "name": "NVIDIA Corporation Device 1b80 (rev a1)", 
        "vendor": "NVIDIA"
      }, 
      "gpu_misc": {}, 
      "os": {
        "bits": "64", 
        "ck_os_base_uoa": "", 
        "ck_os_uoa": "linux-64", 
        "name": "Ubuntu 16.04.1 LTS", 
        "name_long": "Linux-4.4.0-45-generic-x86_64-with-Ubuntu-16.04-xenial", 
        "name_short": "Linux 4.4.0", 
        "serial_number": ""
      }, 
      "os_misc": {}, 
      "platform": {
        "model": "HP Z640 Workstation", 
        "name": "Hewlett-Packard (HP Z640 Workstation)", 
        "vendor": "Hewlett-Packard"
      }, 
      "platform_misc": {}
    }, 
    "statistical_repetitions": 3
  }
}
